Workbook

Sheet Assumptions
A1: LAAA UNDERWRITING BENCHMARKS (edit here; every deal tab reads these)
A3: Vacancy & credit loss (% of GSI) | B3: 0.03 | C3: Standard LA practice; vacant units carried at asking rent inside scheduled GSR
A4: Management fee (% of EGI) | B4: 0.05 | C4: Deal-by-deal agent choice; 5% default, MAX(OM, benchmark) used
A5: Insurance: per unit ($) | B5: 200 | C5: LAAA benchmark = (units x $200) + (gross SF x $1.00)
A6: Insurance: per gross SF ($) | B6: 1
A7: Repairs & maintenance per unit, pre-1990 ($/yr) | B7: 1200
A8: Repairs & maintenance per unit, 1990+ ($/yr) | B8: 800
A9: Utilities per unit, LA City ($/yr) | B9: 1500 | C9: Owner-paid water/sewer/trash/common electric+gas (LA Sanitation bundles trash)
A10: Utilities per unit, Santa Monica ($/yr) | B10: 1800 | C10: Separate trash hauler, higher water rates
A11: Utilities per unit, Beverly Hills / WeHo / Culver ($/yr) | B11: 1600
A12: Contract services per unit ($/yr) | B12: 400 | C12: Landscaping, pest, common-area cleaning
A13: Admin / legal / licenses / rent registration per unit ($/yr) | B13: 250 | C13: Includes RSO/rent-board fees, business license, bookkeeping
A14: Replacement reserves per unit ($/yr) | B14: 300
A15: Property tax rate: Los Angeles City | B15: 0.0125 | C15: Ad valorem + direct assessments, reassessed at purchase price
A16: Property tax rate: Santa Monica | B16: 0.0115
A17: Property tax rate: Beverly Hills | B17: 0.0115
A18: Property tax rate: West Hollywood | B18: 0.012
A19: Property tax rate: Culver City | B19: 0.012
A20: Financing: max LTV | B20: 0.6
A21: Financing: min DCR on LAAA NOI | B21: 1.25 | C21: Loan = lesser of LTV loan and DCR-sized loan
A22: Financing: interest rate | B22: 0.0625
A23: Financing: amortization (years) | B23: 30
A24: OM "light" threshold: LAAA total exceeds OM total by more than | B24: 0.05 | C24: Flags OM EXPENSES LIGHT on the deal tab and Master List
A26: Rent-allocation weights when only GRM is published (relative to 1 Bd)
A27: Studio | B27: 0.7
A28: 1 Bd | B28: 1
A29: 2 Bd | B29: 1.35
A30: 3 Bd | B30: 1.75
A32: Estimated in-place rents when NOTHING is published (orange cells on deal tabs)
A33: Coastal (SM / Venice / WeHo / BH): Studio | B33: 1900
A34: Coastal: 1 Bd | B34: 2400
A35: Coastal: 2 Bd | B35: 3200
A36: Coastal: 3 Bd | B36: 4200
A37: West LA / Palms / Culver: Studio | B37: 1750
A38: West LA / Palms / Culver: 1 Bd | B38: 2200
A39: West LA / Palms / Culver: 2 Bd | B39: 2900
A40: West LA / Palms / Culver: 3 Bd | B40: 3800

Sheet 01 823 5th St
A1: 823 5th St
A2: Santa Monica, CA 90403 | Santa Monica
A3: LoopNet listing | B3: Data pulled 9/17/2026 from LoopNet public listing + LAAA OM extraction (July 2026 intake)
A6: PROPERTY
A7: Units | B7: 10
A8: Gross building SF | B8: 10523
A9: Lot SF | B9: 7405
A10: Lot acres | B10: 0.17
A11: Year built | B11: 1958
A12: Stories | B12: 2
A13: Zoning | B13: R3, Santa Monica
A14: Occupancy per listing | B14: 100%
A15: APN | B15: 4292-009-022
A16: Assessed value (current) | B16: 3582053
A17: Listing broker(s) | B17: William Dawson
A18: Date on market | B18: 1/7/2026
A19: Listing last updated | B19: 9/11/2026
A21: PRICING
A22: Asking price | B22: 4800000
A23: Price per unit | B23: =IFERROR(B22/B7,"") -> 480000
A24: Price per gross SF | B24: =IFERROR(B22/B8,"") -> 456.14369
A25: OM / listing cap rate (as published) | B25: 0.04
A26: OM / listing GRM (as published) | B26: 16
A28: UNIT MIX & SCHEDULED RENT
A29: Unit type | B29: # Units | C29: Avg rent / mo | D29: Monthly total | E29: Annual | F29: Rent source
A30: 2 Bd / 1 Ba (~900 SF) | B30: 6 | C30: 2860 | D30: =B30*C30 -> 17160 | E30: =D30*12 -> 205920 | F30: Allocated from published GRM (price / GRM) using LAAA bed weights
A31: 1 Bd / 1 Ba | B31: 3 | C31: 2119 | D31: =B31*C31 -> 6357 | E31: =D31*12 -> 76284 | F31: Allocated from published GRM (price / GRM) using LAAA bed weights
A32: Studio | B32: 1 | C32: 1483 | D32: =B32*C32 -> 1483 | E32: =D32*12 -> 17796 | F32: Allocated from published GRM (price / GRM) using LAAA bed weights
A33: Total / weighted avg | B33: =SUM(B30:B32) -> 10 | C33: =IFERROR(D33/B33,"") -> 2500 | D33: =SUM(D30:D32) -> 25000 | E33: =SUM(E30:E32) -> 300000
A35: INCOME
B36: OM as presented | C36: LAAA underwritten | F36: Basis / note
A37: Scheduled gross rent | B37: 306216 | C37: =E33 -> 300000 | F37: OM column: OM rent roll
A38: Other income (laundry, parking, RUBS) | B38: 0 | C38: 0
A39: Gross scheduled income | B39: =B37+B38 -> 306216 | C39: =C37+C38 -> 300000
A40: Vacancy & credit loss | B40: =-B37*0.03 -> -9186.48 | C40: =-C37*Assumptions!$B$3 -> -9000 | F40: OM 3.0% (OM figure if extracted, else 3% assumed); LAAA per Assumptions
A41: Effective gross income | B41: =B39+B40 -> 297029.52 | C41: =C39+C40 -> 291000
A43: OPERATING EXPENSES
A44: Expense line | B44: OM as presented | C44: LAAA benchmark | D44: LAAA underwritten | E44: Delta vs OM | F44: Basis / note
A45: Property taxes (reassessed at price) | B45: 57500 | C45: =B22*Assumptions!$B$16 -> 55200 | D45: =C45 -> 55200 | E45: =IF(ISNUMBER(B45),D45-B45,"") -> -2300 | F45: Santa Monica rate x asking price; always reassessed, never MAX
A46: Insurance | C46: =B7*Assumptions!$B$5+B8*Assumptions!$B$6 -> 12523 | D46: =IF(ISNUMBER(B46),MAX(B46,C46),C46) -> 12523 | E46: =IF(ISNUMBER(B46),D46-B46,"") | F46: LAAA benchmark (units x $200) + (SF x $1.00)
A47: Management | C47: =C41*Assumptions!$B$4 -> 14550 | D47: =IF(ISNUMBER(B47),MAX(B47,C47),C47) -> 14550 | E47: =IF(ISNUMBER(B47),D47-B47,"") | F47: % of LAAA EGI
A48: Repairs & maintenance | C48: =B7*Assumptions!$B$7 -> 12000 | D48: =IF(ISNUMBER(B48),MAX(B48,C48),C48) -> 12000 | E48: =IF(ISNUMBER(B48),D48-B48,"") | F48: per unit, by vintage
A49: Utilities (water/sewer/trash/common electric & gas) | C49: =B7*Assumptions!$B$10 -> 18000 | D49: =IF(ISNUMBER(B49),MAX(B49,C49),C49) -> 18000 | E49: =IF(ISNUMBER(B49),D49-B49,"") | F49: per unit, by city
A50: Contract services (landscape, pest, cleaning) | C50: =B7*Assumptions!$B$12 -> 4000 | D50: =IF(ISNUMBER(B50),MAX(B50,C50),C50) -> 4000 | E50: =IF(ISNUMBER(B50),D50-B50,"") | F50: per unit
A51: Admin / legal / licenses / rent registration | C51: =B7*Assumptions!$B$13 -> 2500 | D51: =IF(ISNUMBER(B51),MAX(B51,C51),C51) -> 2500 | E51: =IF(ISNUMBER(B51),D51-B51,"") | F51: per unit; OM "other" items land here
A52: Replacement reserves | C52: =B7*Assumptions!$B$14 -> 3000 | D52: =IF(ISNUMBER(B52),MAX(B52,C52),C52) -> 3000 | E52: =IF(ISNUMBER(B52),D52-B52,"") | F52: per unit
A53: Unallocated / other OM expense items | B53: 48850 | C53: =0 -> 0 | D53: =C53 -> 0 | E53: =IF(ISNUMBER(B53),D53-B53,"") -> -48850 | F53: OM total claimed minus lines mapped above (OM did not itemize; LAAA benchmark lines already cover these costs)
A54: Total operating expenses | B54: =SUM(B45:B53) -> 106350 | C54: =SUM(C45:C53) -> 121773 | D54: =SUM(D45:D53) -> 121773 | E54: =IF(ISNUMBER(B54),D54-B54,"") -> 15423 | F54: OM claimed total 106,350 (lines mapped from OM extraction)
A55: Expenses per unit | B55: =IFERROR(B54/B7,"") -> 10635 | C55: =IFERROR(C54/B7,"") -> 12177.3 | D55: =IFERROR(D54/B7,"") -> 12177.3
A56: Expenses as % of EGI | B56: =IFERROR(B54/B41,"") -> 0.35804522 | C56: =IFERROR(C54/C41,"") -> 0.41846392 | D56: =IF(C37>0,IFERROR(D54/C41,""),"") -> 0.41846392
A57: OM expense test | B57: =IF(ISNUMBER(B54),IF(D54>B54*(1+Assumptions!$B$24),"OM EXPENSES LIGHT","OM expenses reasonable"),"OM expenses not published") -> OM EXPENSES LIGHT
A59: NOI & RETURNS
B60: OM as presented | C60: LAAA underwritten | F60: Basis / note
A61: Net operating income | B61: =B41-B54 -> 190679.52 | C61: =IF(C37>0,C41-D54,"") -> 169227
A62: Cap rate on asking price | B62: =IFERROR(B61/B22,"") -> 0.0397249 | C62: =IF(C61="","",IFERROR(C61/B22,"")) -> 0.035255625 | F62: OM column recomputed from OM figures; compare to published cap above
A63: GRM (price / scheduled rent) | B63: =IFERROR(B22/B37,"") -> 15.67521 | C63: =IF(C37>0,IFERROR(B22/C37,""),"") -> 16
A64: NOI per unit | B64: =IFERROR(B61/B7,"") -> 19067.952 | C64: =IF(C61="","",IFERROR(C61/B7,"")) -> 16922.7
A66: FINANCING (illustrative, on LAAA NOI)
A67: LTV loan | B67: =IFERROR(B22*Assumptions!$B$20,"") -> 2880000
A68: DCR-sized loan | B68: =IF(C61="","",IFERROR(PV(Assumptions!$B$22/12,Assumptions!$B$23*12,-C61/Assumptions!$B$21/12),"")) -> 1832302.2
A69: Loan amount (lesser of) | B69: =IFERROR(MIN(B67,B68),"") -> 1832302.2
A70: Down payment | B70: =IFERROR(B22-B69,"") -> 2967697.8
A71: Annual debt service | B71: =IFERROR(-PMT(Assumptions!$B$22/12,Assumptions!$B$23*12,B69)*12,"") -> 135381.6
A72: DCR | B72: =IFERROR(C61/B71,"") -> 1.25
A73: Cash flow after debt service | B73: =IFERROR(C61-B71,"") -> 33845.4
A74: Cash-on-cash return | B74: =IFERROR(B73/B70,"") -> 0.011404598
A76: Legend: yellow = published input, orange = estimated (nothing published), grey = LAAA underwritten (MAX of OM line and benchmark; taxes always reassessed).
