Workbook

Sheet Assumptions
A1: LAAA UNDERWRITING BENCHMARKS (edit here; every deal tab reads these)
A3: Vacancy & credit loss (% of GSI) | B3: 0.03 | C3: Standard LA practice; vacant units carried at asking rent inside scheduled GSR
A4: Management fee (% of EGI) | B4: 0.05 | C4: Deal-by-deal agent choice; 5% default, MAX(OM, benchmark) used
A5: Insurance: per unit ($) | B5: 200 | C5: LAAA benchmark = (units x $200) + (gross SF x $1.00)
A6: Insurance: per gross SF ($) | B6: 1
A7: Repairs & maintenance per unit, pre-1990 ($/yr) | B7: 1200
A8: Repairs & maintenance per unit, 1990+ ($/yr) | B8: 800
A9: Utilities per unit, LA City ($/yr) | B9: 1500 | C9: Owner-paid water/sewer/trash/common electric+gas (LA Sanitation bundles trash)
A10: Utilities per unit, Santa Monica ($/yr) | B10: 1800 | C10: Separate trash hauler, higher water rates
A11: Utilities per unit, Beverly Hills / WeHo / Culver ($/yr) | B11: 1600
A12: Contract services per unit ($/yr) | B12: 400 | C12: Landscaping, pest, common-area cleaning
A13: Admin / legal / licenses / rent registration per unit ($/yr) | B13: 250 | C13: Includes RSO/rent-board fees, business license, bookkeeping
A14: Replacement reserves per unit ($/yr) | B14: 300
A15: Property tax rate: Los Angeles City | B15: 0.0125 | C15: Ad valorem + direct assessments, reassessed at purchase price
A16: Property tax rate: Santa Monica | B16: 0.0115
A17: Property tax rate: Beverly Hills | B17: 0.0115
A18: Property tax rate: West Hollywood | B18: 0.012
A19: Property tax rate: Culver City | B19: 0.012
A20: Financing: max LTV | B20: 0.6
A21: Financing: min DCR on LAAA NOI | B21: 1.25 | C21: Loan = lesser of LTV loan and DCR-sized loan
A22: Financing: interest rate | B22: 0.0625
A23: Financing: amortization (years) | B23: 30
A24: OM "light" threshold: LAAA total exceeds OM total by more than | B24: 0.05 | C24: Flags OM EXPENSES LIGHT on the deal tab and Master List
A26: Rent-allocation weights when only GRM is published (relative to 1 Bd)
A27: Studio | B27: 0.7
A28: 1 Bd | B28: 1
A29: 2 Bd | B29: 1.35
A30: 3 Bd | B30: 1.75
A32: Estimated in-place rents when NOTHING is published (orange cells on deal tabs)
A33: Coastal (SM / Venice / WeHo / BH): Studio | B33: 1900
A34: Coastal: 1 Bd | B34: 2400
A35: Coastal: 2 Bd | B35: 3200
A36: Coastal: 3 Bd | B36: 4200
A37: West LA / Palms / Culver: Studio | B37: 1750
A38: West LA / Palms / Culver: 1 Bd | B38: 2200
A39: West LA / Palms / Culver: 2 Bd | B39: 2900
A40: West LA / Palms / Culver: 3 Bd | B40: 3800

Sheet 02 1129 Lincoln Blvd
A1: 1129 Lincoln Blvd
A2: Santa Monica, CA 90403 | Santa Monica
A3: LoopNet listing | B3: Data pulled 9/17/2026 from LoopNet public listing
A6: PROPERTY
A7: Units | B7: 10
A8: Gross building SF | B8: 7377
A9: Lot SF | B9: 7405
A10: Lot acres | B10: 0.17
A11: Year built | B11: 1956
A12: Stories | B12: 1
A13: Zoning | B13: SMR3AY - Santa Monica R2 - Multi-Residential
A14: Occupancy per listing | B14: 100%
A15: APN | B15: 4281-035-016
A16: Assessed value (current) | B16: 787301
A17: Listing broker(s) | B17: Stephen Lampe
A18: Date on market | B18: 3/9/2026
A19: Listing last updated | B19: 8/18/2026
A21: PRICING
A22: Asking price | B22: 3100000
A23: Price per unit | B23: =IFERROR(B22/B7,"") -> 310000
A24: Price per gross SF | B24: =IFERROR(B22/B8,"") -> 420.22502
A25: OM / listing cap rate (as published) | B25: 0.0632
A26: OM / listing GRM (as published) | B26: 11.16
A28: UNIT MIX & SCHEDULED RENT
A29: Unit type | B29: # Units | C29: Avg rent / mo | D29: Monthly total | E29: Annual | F29: Rent source
A30: 2 Bd / 2 Ba | B30: 1 | C30: 2296 | D30: =B30*C30 -> 2296 | E30: =D30*12 -> 27552 | F30: LoopNet published avg rent by unit type
A31: 2 Bd / 1.5 Ba | B31: 1 | C31: 2840 | D31: =B31*C31 -> 2840 | E31: =D31*12 -> 34080 | F31: LoopNet published avg rent by unit type
A32: 2 Bd / 1 Ba | B32: 1 | C32: 2995 | D32: =B32*C32 -> 2995 | E32: =D32*12 -> 35940 | F32: LoopNet published avg rent by unit type
A33: 1 Bd / 1 Ba | B33: 5 | C33: 2300 | D33: =B33*C33 -> 11500 | E33: =D33*12 -> 138000 | F33: LoopNet published avg rent by unit type
A34: Studio | B34: 2 | C34: 1922 | D34: =B34*C34 -> 3844 | E34: =D34*12 -> 46128 | F34: LoopNet published avg rent by unit type
A35: Total / weighted avg | B35: =SUM(B30:B34) -> 10 | C35: =IFERROR(D35/B35,"") -> 2347.5 | D35: =SUM(D30:D34) -> 23475 | E35: =SUM(E30:E34) -> 281700
A37: INCOME
B38: OM as presented | C38: LAAA underwritten | F38: Basis / note
A39: Scheduled gross rent | B39: 277777.78 | C39: =E35 -> 281700 | F39: OM column: price / published GRM
A40: Other income (laundry, parking, RUBS) | B40: 0 | C40: 0
A41: Gross scheduled income | B41: =B39+B40 -> 277777.78 | C41: =C39+C40 -> 281700
A42: Vacancy & credit loss | B42: =-B39*0.03 -> -8333.3333 | C42: =-C39*Assumptions!$B$3 -> -8451 | F42: OM 3.0% (OM figure if extracted, else 3% assumed); LAAA per Assumptions
A43: Effective gross income | B43: =B41+B42 -> 269444.44 | C43: =C41+C42 -> 273249
A45: OPERATING EXPENSES
A46: Expense line | B46: OM as presented | C46: LAAA benchmark | D46: LAAA underwritten | E46: Delta vs OM | F46: Basis / note
A47: Property taxes (reassessed at price) | C47: =B22*Assumptions!$B$16 -> 35650 | D47: =C47 -> 35650 | E47: =IF(ISNUMBER(B47),D47-B47,"") | F47: Santa Monica rate x asking price; always reassessed, never MAX
A48: Insurance | C48: =B7*Assumptions!$B$5+B8*Assumptions!$B$6 -> 9377 | D48: =IF(ISNUMBER(B48),MAX(B48,C48),C48) -> 9377 | E48: =IF(ISNUMBER(B48),D48-B48,"") | F48: LAAA benchmark (units x $200) + (SF x $1.00)
A49: Management | C49: =C43*Assumptions!$B$4 -> 13662.45 | D49: =IF(ISNUMBER(B49),MAX(B49,C49),C49) -> 13662.45 | E49: =IF(ISNUMBER(B49),D49-B49,"") | F49: % of LAAA EGI
A50: Repairs & maintenance | C50: =B7*Assumptions!$B$7 -> 12000 | D50: =IF(ISNUMBER(B50),MAX(B50,C50),C50) -> 12000 | E50: =IF(ISNUMBER(B50),D50-B50,"") | F50: per unit, by vintage
A51: Utilities (water/sewer/trash/common electric & gas) | C51: =B7*Assumptions!$B$10 -> 18000 | D51: =IF(ISNUMBER(B51),MAX(B51,C51),C51) -> 18000 | E51: =IF(ISNUMBER(B51),D51-B51,"") | F51: per unit, by city
A52: Contract services (landscape, pest, cleaning) | C52: =B7*Assumptions!$B$12 -> 4000 | D52: =IF(ISNUMBER(B52),MAX(B52,C52),C52) -> 4000 | E52: =IF(ISNUMBER(B52),D52-B52,"") | F52: per unit
A53: Admin / legal / licenses / rent registration | C53: =B7*Assumptions!$B$13 -> 2500 | D53: =IF(ISNUMBER(B53),MAX(B53,C53),C53) -> 2500 | E53: =IF(ISNUMBER(B53),D53-B53,"") | F53: per unit; OM "other" items land here
A54: Replacement reserves | C54: =B7*Assumptions!$B$14 -> 3000 | D54: =IF(ISNUMBER(B54),MAX(B54,C54),C54) -> 3000 | E54: =IF(ISNUMBER(B54),D54-B54,"") | F54: per unit
A55: Total operating expenses | B55: =B43-B22*B25 -> 73524.444 | C55: =SUM(C47:C54) -> 98189.45 | D55: =SUM(D47:D54) -> 98189.45 | E55: =IF(ISNUMBER(B55),D55-B55,"") -> 24665.006 | F55: OM line items not published. OM total IMPLIED = OM EGI - (price x published cap)
A56: Expenses per unit | B56: =IFERROR(B55/B7,"") -> 7352.4444 | C56: =IFERROR(C55/B7,"") -> 9818.945 | D56: =IFERROR(D55/B7,"") -> 9818.945
A57: Expenses as % of EGI | B57: =IFERROR(B55/B43,"") -> 0.27287423 | C57: =IFERROR(C55/C43,"") -> 0.35934056 | D57: =IF(C39>0,IFERROR(D55/C43,""),"") -> 0.35934056
A58: OM expense test | B58: =IF(ISNUMBER(B55),IF(D55>B55*(1+Assumptions!$B$24),"OM EXPENSES LIGHT","OM expenses reasonable"),"OM expenses not published") -> OM EXPENSES LIGHT
A60: NOI & RETURNS
B61: OM as presented | C61: LAAA underwritten | F61: Basis / note
A62: Net operating income | B62: =B43-B55 -> 195920 | C62: =IF(C39>0,C43-D55,"") -> 175059.55
A63: Cap rate on asking price | B63: =IFERROR(B62/B22,"") -> 0.0632 | C63: =IF(C62="","",IFERROR(C62/B22,"")) -> 0.056470823 | F63: OM column recomputed from OM figures; compare to published cap above
A64: GRM (price / scheduled rent) | B64: =IFERROR(B22/B39,"") -> 11.16 | C64: =IF(C39>0,IFERROR(B22/C39,""),"") -> 11.004615
A65: NOI per unit | B65: =IFERROR(B62/B7,"") -> 19592 | C65: =IF(C62="","",IFERROR(C62/B7,"")) -> 17505.955
A67: FINANCING (illustrative, on LAAA NOI)
A68: LTV loan | B68: =IFERROR(B22*Assumptions!$B$20,"") -> 1860000
A69: DCR-sized loan | B69: =IF(C62="","",IFERROR(PV(Assumptions!$B$22/12,Assumptions!$B$23*12,-C62/Assumptions!$B$21/12),"")) -> 1895454.1
A70: Loan amount (lesser of) | B70: =IFERROR(MIN(B68,B69),"") -> 1860000
A71: Down payment | B71: =IFERROR(B22-B70,"") -> 1240000
A72: Annual debt service | B72: =IFERROR(-PMT(Assumptions!$B$22/12,Assumptions!$B$23*12,B70)*12,"") -> 137428.08
A73: DCR | B73: =IFERROR(C62/B72,"") -> 1.2738267
A74: Cash flow after debt service | B74: =IFERROR(C62-B72,"") -> 37631.471
A75: Cash-on-cash return | B75: =IFERROR(B74/B71,"") -> 0.03034796
A77: Legend: yellow = published input, orange = estimated (nothing published), grey = LAAA underwritten (MAX of OM line and benchmark; taxes always reassessed).
