Workbook

Sheet Assumptions
A1: LAAA UNDERWRITING BENCHMARKS (edit here; every deal tab reads these)
A3: Vacancy & credit loss (% of GSI) | B3: 0.03 | C3: Standard LA practice; vacant units carried at asking rent inside scheduled GSR
A4: Management fee (% of EGI) | B4: 0.05 | C4: Deal-by-deal agent choice; 5% default, MAX(OM, benchmark) used
A5: Insurance: per unit ($) | B5: 200 | C5: LAAA benchmark = (units x $200) + (gross SF x $1.00)
A6: Insurance: per gross SF ($) | B6: 1
A7: Repairs & maintenance per unit, pre-1990 ($/yr) | B7: 1200
A8: Repairs & maintenance per unit, 1990+ ($/yr) | B8: 800
A9: Utilities per unit, LA City ($/yr) | B9: 1500 | C9: Owner-paid water/sewer/trash/common electric+gas (LA Sanitation bundles trash)
A10: Utilities per unit, Santa Monica ($/yr) | B10: 1800 | C10: Separate trash hauler, higher water rates
A11: Utilities per unit, Beverly Hills / WeHo / Culver ($/yr) | B11: 1600
A12: Contract services per unit ($/yr) | B12: 400 | C12: Landscaping, pest, common-area cleaning
A13: Admin / legal / licenses / rent registration per unit ($/yr) | B13: 250 | C13: Includes RSO/rent-board fees, business license, bookkeeping
A14: Replacement reserves per unit ($/yr) | B14: 300
A15: Property tax rate: Los Angeles City | B15: 0.0125 | C15: Ad valorem + direct assessments, reassessed at purchase price
A16: Property tax rate: Santa Monica | B16: 0.0115
A17: Property tax rate: Beverly Hills | B17: 0.0115
A18: Property tax rate: West Hollywood | B18: 0.012
A19: Property tax rate: Culver City | B19: 0.012
A20: Financing: max LTV | B20: 0.6
A21: Financing: min DCR on LAAA NOI | B21: 1.25 | C21: Loan = lesser of LTV loan and DCR-sized loan
A22: Financing: interest rate | B22: 0.0625
A23: Financing: amortization (years) | B23: 30
A24: OM "light" threshold: LAAA total exceeds OM total by more than | B24: 0.05 | C24: Flags OM EXPENSES LIGHT on the deal tab and Master List
A26: Rent-allocation weights when only GRM is published (relative to 1 Bd)
A27: Studio | B27: 0.7
A28: 1 Bd | B28: 1
A29: 2 Bd | B29: 1.35
A30: 3 Bd | B30: 1.75
A32: Estimated in-place rents when NOTHING is published (orange cells on deal tabs)
A33: Coastal (SM / Venice / WeHo / BH): Studio | B33: 1900
A34: Coastal: 1 Bd | B34: 2400
A35: Coastal: 2 Bd | B35: 3200
A36: Coastal: 3 Bd | B36: 4200
A37: West LA / Palms / Culver: Studio | B37: 1750
A38: West LA / Palms / Culver: 1 Bd | B38: 2200
A39: West LA / Palms / Culver: 2 Bd | B39: 2900
A40: West LA / Palms / Culver: 3 Bd | B40: 3800

Sheet 03 2001 Penmar Ave
A1: 2001 Penmar Ave
A2: Venice, CA 90291 | Venice
A3: LoopNet listing | B3: Data pulled 9/17/2026 from LoopNet public listing
A4: NOTE: New listing 9/15/26, remodeled
A6: PROPERTY
A7: Units | B7: 14
A8: Gross building SF | B8: 9532
A9: Lot SF | B9: 10019
A10: Lot acres | B10: 0.23
A11: Year built | B11: 1962
A12: Stories | B12: 2
A13: Zoning | B13: R3, Los Angeles - Multiple Family Dwelling Residential
A14: Occupancy per listing | B14: 100%
A15: APN | B15: 4242-009-011
A16: Assessed value (current) | B16: 3993440
A17: Listing broker(s) | B17: Jonathan Taksa
A18: Date on market | B18: 9/15/2026
A19: Listing last updated | B19: 9/15/2026
A21: PRICING
A22: Asking price | B22: 5095000
A23: Price per unit | B23: =IFERROR(B22/B7,"") -> 363928.57
A24: Price per gross SF | B24: =IFERROR(B22/B8,"") -> 534.51532
A25: OM / listing cap rate (as published) | B25: 0.062
A26: OM / listing GRM (as published) | B26: 11.34
A28: UNIT MIX & SCHEDULED RENT
A29: Unit type | B29: # Units | C29: Avg rent / mo | D29: Monthly total | E29: Annual | F29: Rent source
A30: Studio (~450 SF) | B30: 2 | C30: 1618 | D30: =B30*C30 -> 3236 | E30: =D30*12 -> 38832 | F30: Allocated from published GRM (price / GRM) using LAAA bed weights
A31: 1 Bd / 1 Ba (~625 SF) | B31: 4 | C31: 2311 | D31: =B31*C31 -> 9244 | E31: =D31*12 -> 110928 | F31: Allocated from published GRM (price / GRM) using LAAA bed weights
A32: 2 Bd / 1 Ba (~758 SF) | B32: 5 | C32: 3120 | D32: =B32*C32 -> 15600 | E32: =D32*12 -> 187200 | F32: Allocated from published GRM (price / GRM) using LAAA bed weights
A33: 2 Bd / 2 Ba (~758 SF) | B33: 3 | C33: 3120 | D33: =B33*C33 -> 9360 | E33: =D33*12 -> 112320 | F33: Allocated from published GRM (price / GRM) using LAAA bed weights
A34: Total / weighted avg | B34: =SUM(B30:B33) -> 14 | C34: =IFERROR(D34/B34,"") -> 2674.2857 | D34: =SUM(D30:D33) -> 37440 | E34: =SUM(E30:E33) -> 449280
A36: INCOME
B37: OM as presented | C37: LAAA underwritten | F37: Basis / note
A38: Scheduled gross rent | B38: 449294.53 | C38: =E34 -> 449280 | F38: OM column: price / published GRM
A39: Other income (laundry, parking, RUBS) | B39: 0 | C39: 0
A40: Gross scheduled income | B40: =B38+B39 -> 449294.53 | C40: =C38+C39 -> 449280
A41: Vacancy & credit loss | B41: =-B38*0.03 -> -13478.836 | C41: =-C38*Assumptions!$B$3 -> -13478.4 | F41: OM 3.0% (OM figure if extracted, else 3% assumed); LAAA per Assumptions
A42: Effective gross income | B42: =B40+B41 -> 435815.7 | C42: =C40+C41 -> 435801.6
A44: OPERATING EXPENSES
A45: Expense line | B45: OM as presented | C45: LAAA benchmark | D45: LAAA underwritten | E45: Delta vs OM | F45: Basis / note
A46: Property taxes (reassessed at price) | C46: =B22*Assumptions!$B$15 -> 63687.5 | D46: =C46 -> 63687.5 | E46: =IF(ISNUMBER(B46),D46-B46,"") | F46: Los Angeles rate x asking price; always reassessed, never MAX
A47: Insurance | C47: =B7*Assumptions!$B$5+B8*Assumptions!$B$6 -> 12332 | D47: =IF(ISNUMBER(B47),MAX(B47,C47),C47) -> 12332 | E47: =IF(ISNUMBER(B47),D47-B47,"") | F47: LAAA benchmark (units x $200) + (SF x $1.00)
A48: Management | C48: =C42*Assumptions!$B$4 -> 21790.08 | D48: =IF(ISNUMBER(B48),MAX(B48,C48),C48) -> 21790.08 | E48: =IF(ISNUMBER(B48),D48-B48,"") | F48: % of LAAA EGI
A49: Repairs & maintenance | C49: =B7*Assumptions!$B$7 -> 16800 | D49: =IF(ISNUMBER(B49),MAX(B49,C49),C49) -> 16800 | E49: =IF(ISNUMBER(B49),D49-B49,"") | F49: per unit, by vintage
A50: Utilities (water/sewer/trash/common electric & gas) | C50: =B7*Assumptions!$B$9 -> 21000 | D50: =IF(ISNUMBER(B50),MAX(B50,C50),C50) -> 21000 | E50: =IF(ISNUMBER(B50),D50-B50,"") | F50: per unit, by city
A51: Contract services (landscape, pest, cleaning) | C51: =B7*Assumptions!$B$12 -> 5600 | D51: =IF(ISNUMBER(B51),MAX(B51,C51),C51) -> 5600 | E51: =IF(ISNUMBER(B51),D51-B51,"") | F51: per unit
A52: Admin / legal / licenses / rent registration | C52: =B7*Assumptions!$B$13 -> 3500 | D52: =IF(ISNUMBER(B52),MAX(B52,C52),C52) -> 3500 | E52: =IF(ISNUMBER(B52),D52-B52,"") | F52: per unit; OM "other" items land here
A53: Replacement reserves | C53: =B7*Assumptions!$B$14 -> 4200 | D53: =IF(ISNUMBER(B53),MAX(B53,C53),C53) -> 4200 | E53: =IF(ISNUMBER(B53),D53-B53,"") | F53: per unit
A54: Total operating expenses | B54: =B42-B22*B25 -> 119925.7 | C54: =SUM(C46:C53) -> 148909.58 | D54: =SUM(D46:D53) -> 148909.58 | E54: =IF(ISNUMBER(B54),D54-B54,"") -> 28983.883 | F54: OM line items not published. OM total IMPLIED = OM EGI - (price x published cap)
A55: Expenses per unit | B55: =IFERROR(B54/B7,"") -> 8566.1212 | C55: =IFERROR(C54/B7,"") -> 10636.399 | D55: =IFERROR(D54/B7,"") -> 10636.399
A56: Expenses as % of EGI | B56: =IFERROR(B54/B42,"") -> 0.27517526 | C56: =IFERROR(C54/C42,"") -> 0.34169122 | D56: =IF(C38>0,IFERROR(D54/C42,""),"") -> 0.34169122
A57: OM expense test | B57: =IF(ISNUMBER(B54),IF(D54>B54*(1+Assumptions!$B$24),"OM EXPENSES LIGHT","OM expenses reasonable"),"OM expenses not published") -> OM EXPENSES LIGHT
A59: NOI & RETURNS
B60: OM as presented | C60: LAAA underwritten | F60: Basis / note
A61: Net operating income | B61: =B42-B54 -> 315890 | C61: =IF(C38>0,C42-D54,"") -> 286892.02
A62: Cap rate on asking price | B62: =IFERROR(B61/B22,"") -> 0.062 | C62: =IF(C61="","",IFERROR(C61/B22,"")) -> 0.056308542 | F62: OM column recomputed from OM figures; compare to published cap above
A63: GRM (price / scheduled rent) | B63: =IFERROR(B22/B38,"") -> 11.34 | C63: =IF(C38>0,IFERROR(B22/C38,""),"") -> 11.340367
A64: NOI per unit | B64: =IFERROR(B61/B7,"") -> 22563.571 | C64: =IF(C61="","",IFERROR(C61/B7,"")) -> 20492.287
A66: FINANCING (illustrative, on LAAA NOI)
A67: LTV loan | B67: =IFERROR(B22*Assumptions!$B$20,"") -> 3057000
A68: DCR-sized loan | B68: =IF(C61="","",IFERROR(PV(Assumptions!$B$22/12,Assumptions!$B$23*12,-C61/Assumptions!$B$21/12),"")) -> 3106318.1
A69: Loan amount (lesser of) | B69: =IFERROR(MIN(B67,B68),"") -> 3057000
A70: Down payment | B70: =IFERROR(B22-B69,"") -> 2038000
A71: Annual debt service | B71: =IFERROR(-PMT(Assumptions!$B$22/12,Assumptions!$B$23*12,B69)*12,"") -> 225869.7
A72: DCR | B72: =IFERROR(C61/B71,"") -> 1.270166
A73: Cash flow after debt service | B73: =IFERROR(C61-B71,"") -> 61022.322
A74: Cash-on-cash return | B74: =IFERROR(B73/B70,"") -> 0.029942258
A76: Legend: yellow = published input, orange = estimated (nothing published), grey = LAAA underwritten (MAX of OM line and benchmark; taxes always reassessed).
