Workbook

Sheet Assumptions
A1: LAAA UNDERWRITING BENCHMARKS (edit here; every deal tab reads these)
A3: Vacancy & credit loss (% of GSI) | B3: 0.03 | C3: Standard LA practice; vacant units carried at asking rent inside scheduled GSR
A4: Management fee (% of EGI) | B4: 0.05 | C4: Deal-by-deal agent choice; 5% default, MAX(OM, benchmark) used
A5: Insurance: per unit ($) | B5: 200 | C5: LAAA benchmark = (units x $200) + (gross SF x $1.00)
A6: Insurance: per gross SF ($) | B6: 1
A7: Repairs & maintenance per unit, pre-1990 ($/yr) | B7: 1200
A8: Repairs & maintenance per unit, 1990+ ($/yr) | B8: 800
A9: Utilities per unit, LA City ($/yr) | B9: 1500 | C9: Owner-paid water/sewer/trash/common electric+gas (LA Sanitation bundles trash)
A10: Utilities per unit, Santa Monica ($/yr) | B10: 1800 | C10: Separate trash hauler, higher water rates
A11: Utilities per unit, Beverly Hills / WeHo / Culver ($/yr) | B11: 1600
A12: Contract services per unit ($/yr) | B12: 400 | C12: Landscaping, pest, common-area cleaning
A13: Admin / legal / licenses / rent registration per unit ($/yr) | B13: 250 | C13: Includes RSO/rent-board fees, business license, bookkeeping
A14: Replacement reserves per unit ($/yr) | B14: 300
A15: Property tax rate: Los Angeles City | B15: 0.0125 | C15: Ad valorem + direct assessments, reassessed at purchase price
A16: Property tax rate: Santa Monica | B16: 0.0115
A17: Property tax rate: Beverly Hills | B17: 0.0115
A18: Property tax rate: West Hollywood | B18: 0.012
A19: Property tax rate: Culver City | B19: 0.012
A20: Financing: max LTV | B20: 0.6
A21: Financing: min DCR on LAAA NOI | B21: 1.25 | C21: Loan = lesser of LTV loan and DCR-sized loan
A22: Financing: interest rate | B22: 0.0625
A23: Financing: amortization (years) | B23: 30
A24: OM "light" threshold: LAAA total exceeds OM total by more than | B24: 0.05 | C24: Flags OM EXPENSES LIGHT on the deal tab and Master List
A26: Rent-allocation weights when only GRM is published (relative to 1 Bd)
A27: Studio | B27: 0.7
A28: 1 Bd | B28: 1
A29: 2 Bd | B29: 1.35
A30: 3 Bd | B30: 1.75
A32: Estimated in-place rents when NOTHING is published (orange cells on deal tabs)
A33: Coastal (SM / Venice / WeHo / BH): Studio | B33: 1900
A34: Coastal: 1 Bd | B34: 2400
A35: Coastal: 2 Bd | B35: 3200
A36: Coastal: 3 Bd | B36: 4200
A37: West LA / Palms / Culver: Studio | B37: 1750
A38: West LA / Palms / Culver: 1 Bd | B38: 2200
A39: West LA / Palms / Culver: 2 Bd | B39: 2900
A40: West LA / Palms / Culver: 3 Bd | B40: 3800

Sheet 03 947-953 11th St
A1: 947-953 11th St (Voss Apartments)
A2: Santa Monica, CA 90403 | Santa Monica
A3: LoopNet listing | B3: Data pulled 9/17/2026 from LoopNet public listing + rent roll and expenses read from the listing broker's OM (Equity Union Commercial (The Appel Group), Eliyahu Appel, undated, sale comps through May 2026)
A4: NOTE: 80% occupied per LoopNet | OM: Mills Act: existing recorded Mills Act contract; OM carries property taxes at $36,816 (current bill approx $36,000) on the assumption the contract transfers to the buyer with no reassessment at the $8.5M price. A standard 1.2% reassessment would be approx $102,000. Verify the contract terms and pres
A6: PROPERTY
A7: Units | B7: 15
A8: Gross building SF | B8: 11850
A9: Lot SF | B9: 14810
A10: Lot acres | B10: 0.34
A11: Year built | B11: 1937
A12: Stories | B12: 2
A13: Zoning | B13: SMR2*
A14: Occupancy per listing | B14: 80%
A15: APN | B15: Multiple
A16: Assessed value (current) | B16: 2731000
A17: Listing broker(s) | B17: Eli Appel
A18: Date on market | B18: 9/4/2026
A19: Listing last updated | B19: 9/14/2026
A21: PRICING
A22: Asking price | B22: 8500000
A23: Price per unit | B23: =IFERROR(B22/B7,"") -> 566666.67
A24: Price per gross SF | B24: =IFERROR(B22/B8,"") -> 717.29958
A25: OM / listing cap rate (as published) | B25: 0.0604
A26: OM / listing GRM (as published) | B26: 13.77
A28: UNIT MIX & SCHEDULED RENT
A29: Unit type | B29: # Units | C29: Avg rent / mo | D29: Monthly total | E29: Annual | F29: Rent source
A30: 2 Bd / 2 Ba townhouse [953 #3 townhouse with private yard; market $6,000] | B30: 1 | C30: 5080 | D30: =B30*C30 -> 5080 | E30: =D30*12 -> 60960 | F30: OM rent roll, current in-place rents (OM undated, sale comps through May 2026)
A31: 2 Bd / 1 Ba [range $973-$4,187 occupied; includes 1 vacant unit carried a] | B31: 4 | C31: 3386 | D31: =B31*C31 -> 13544 | E31: =D31*12 -> 162528 | F31: OM rent roll, current in-place rents (OM undated, sale comps through May 2026)
A32: 1 Bd / 1 Ba [range $2,118-$3,960; market $4,000] | B32: 6 | C32: 3373 | D32: =B32*C32 -> 20238 | E32: =D32*12 -> 242856 | F32: OM rent roll, current in-place rents (OM undated, sale comps through May 2026)
A33: Studio [range $1,989-$2,868; market $3,000] | B33: 4 | C33: 2537 | D33: =B33*C33 -> 10148 | E33: =D33*12 -> 121776 | F33: OM rent roll, current in-place rents (OM undated, sale comps through May 2026)
A34: Total / weighted avg | B34: =SUM(B30:B33) -> 15 | C34: =IFERROR(D34/B34,"") -> 3267.3333 | D34: =SUM(D30:D33) -> 49010 | E34: =SUM(E30:E33) -> 588120
A36: INCOME
B37: OM as presented | C37: LAAA underwritten | F37: Basis / note
A38: Scheduled gross rent | B38: 588114 | C38: =E34 -> 588120 | F38: OM column: OM stated current scheduled rent (OM undated, sale comps through May 2026); LAAA column: OM rent roll by unit type
A39: Other income (laundry, parking, RUBS) | B39: 29340 | C39: 29340
A40: Gross scheduled income | B40: =B38+B39 -> 617454 | C40: =C38+C39 -> 617460
A41: Vacancy & credit loss | B41: =-B38*0.03 -> -17643.42 | C41: =-C38*Assumptions!$B$3 -> -17643.6 | F41: OM 3.0%; LAAA per Assumptions
A42: Effective gross income | B42: =B40+B41 -> 599810.58 | C42: =C40+C41 -> 599816.4
A44: OPERATING EXPENSES
A45: Expense line | B45: OM as presented | C45: LAAA benchmark | D45: LAAA underwritten | E45: Delta vs OM | F45: Basis / note
A46: Property taxes (reassessed at price) | B46: 36816 | C46: =B22*Assumptions!$B$16 -> 97750 | D46: =C46 -> 97750 | E46: =IF(ISNUMBER(B46),D46-B46,"") -> 60934 | F46: Santa Monica rate x asking price; always reassessed, never MAX
A47: Insurance | B47: 14578 | C47: =B7*Assumptions!$B$5+B8*Assumptions!$B$6 -> 14850 | D47: =IF(ISNUMBER(B47),MAX(B47,C47),C47) -> 14850 | E47: =IF(ISNUMBER(B47),D47-B47,"") -> 272 | F47: LAAA benchmark (units x $200) + (SF x $1.00)
A48: Management | B48: 23971 | C48: =C42*Assumptions!$B$4 -> 29990.82 | D48: =IF(ISNUMBER(B48),MAX(B48,C48),C48) -> 29990.82 | E48: =IF(ISNUMBER(B48),D48-B48,"") -> 6019.82 | F48: % of LAAA EGI
A49: Repairs & maintenance | B49: 6000 | C49: =B7*Assumptions!$B$7 -> 18000 | D49: =IF(ISNUMBER(B49),MAX(B49,C49),C49) -> 18000 | E49: =IF(ISNUMBER(B49),D49-B49,"") -> 12000 | F49: per unit, by vintage
A50: Utilities (water/sewer/trash/common electric & gas) | B50: 12981 | C50: =B7*Assumptions!$B$10 -> 27000 | D50: =IF(ISNUMBER(B50),MAX(B50,C50),C50) -> 27000 | E50: =IF(ISNUMBER(B50),D50-B50,"") -> 14019 | F50: per unit, by city; OM utilities + water/sewer + gas/electric + trash combined
A51: Contract services (landscape, pest, cleaning) | B51: 1920 | C51: =B7*Assumptions!$B$12 -> 6000 | D51: =IF(ISNUMBER(B51),MAX(B51,C51),C51) -> 6000 | E51: =IF(ISNUMBER(B51),D51-B51,"") -> 4080 | F51: per unit
A52: Admin / legal / licenses / rent registration / other OM items | B52: 4232 | C52: =B7*Assumptions!$B$13 -> 3750 | D52: =IF(ISNUMBER(B52),MAX(B52,C52),C52) -> 4232 | E52: =IF(ISNUMBER(B52),D52-B52,"") -> 0 | F52: OM other items: General & Administrative 4,232
A53: Replacement reserves | C53: =B7*Assumptions!$B$14 -> 4500 | D53: =IF(ISNUMBER(B53),MAX(B53,C53),C53) -> 4500 | E53: =IF(ISNUMBER(B53),D53-B53,"") | F53: per unit
A54: Total operating expenses | B54: =SUM(B46:B53) -> 100498 | C54: =SUM(C46:C53) -> 201840.82 | D54: =SUM(D46:D53) -> 202322.82 | E54: =IF(ISNUMBER(B54),D54-B54,"") -> 101824.82 | F54: OM line items from OM (OM undated, sale comps through May 2026); basis: OM 'Current' column of Annualized Operating Data (p.16); broker figures, not owner actuals. Taxes $36,816 = current bill under the existing recorded Mills Act contract (OM says approx $36,000), NOT a reassessment at the $8.5M price. Management = 4.0% of EGI. Utilities is a single combined line. Market column identical except management $30,019 (4% of market EGI).; OM total 100,498
A55: Expenses per unit | B55: =IFERROR(B54/B7,"") -> 6699.8667 | C55: =IFERROR(C54/B7,"") -> 13456.055 | D55: =IFERROR(D54/B7,"") -> 13488.188
A56: Expenses as % of EGI | B56: =IFERROR(B54/B42,"") -> 0.16754956 | C56: =IFERROR(C54/C42,"") -> 0.33650434 | D56: =IF(C38>0,IFERROR(D54/C42,""),"") -> 0.33730792
A57: OM expense test | B57: =IF(ISNUMBER(B54),IF(D54>B54*(1+Assumptions!$B$24),"OM EXPENSES LIGHT","OM expenses reasonable"),"OM expenses not published") -> OM EXPENSES LIGHT
A59: NOI & RETURNS
B60: OM as presented | C60: LAAA underwritten | F60: Basis / note
A61: Net operating income | B61: =B42-B54 -> 499312.58 | C61: =IF(C38>0,C42-D54,"") -> 397493.58 | F61: OM states NOI 498,774 / cap 5.87
A62: Cap rate on asking price | B62: =IFERROR(B61/B22,"") -> 0.058742656 | C62: =IF(C61="","",IFERROR(C61/B22,"")) -> 0.046763951 | F62: OM column recomputed from OM figures; compare to published cap above
A63: GRM (price / scheduled rent) | B63: =IFERROR(B22/B38,"") -> 14.45298 | C63: =IF(C38>0,IFERROR(B22/C38,""),"") -> 14.452833
A64: NOI per unit | B64: =IFERROR(B61/B7,"") -> 33287.505 | C64: =IF(C61="","",IFERROR(C61/B7,"")) -> 26499.572
A66: FINANCING (illustrative, on LAAA NOI)
A67: LTV loan | B67: =IFERROR(B22*Assumptions!$B$20,"") -> 5100000
A68: DCR-sized loan | B68: =IF(C61="","",IFERROR(PV(Assumptions!$B$22/12,Assumptions!$B$23*12,-C61/Assumptions!$B$21/12),"")) -> 4303854.4
A69: Loan amount (lesser of) | B69: =IFERROR(MIN(B67,B68),"") -> 4303854.4
A70: Down payment | B70: =IFERROR(B22-B69,"") -> 4196145.6
A71: Annual debt service | B71: =IFERROR(-PMT(Assumptions!$B$22/12,Assumptions!$B$23*12,B69)*12,"") -> 317994.86
A72: DCR | B72: =IFERROR(C61/B71,"") -> 1.25
A73: Cash flow after debt service | B73: =IFERROR(C61-B71,"") -> 79498.716
A74: Cash-on-cash return | B74: =IFERROR(B73/B70,"") -> 0.018945653
A76: Legend: yellow = published input, orange = estimated (nothing published), grey = LAAA underwritten (MAX of OM line and benchmark; taxes always reassessed).
