Workbook

Sheet Assumptions
A1: LAAA UNDERWRITING BENCHMARKS (edit here; every deal tab reads these)
A3: Vacancy & credit loss (% of GSI) | B3: 0.03 | C3: Standard LA practice; vacant units carried at asking rent inside scheduled GSR
A4: Management fee (% of EGI) | B4: 0.05 | C4: Deal-by-deal agent choice; 5% default, MAX(OM, benchmark) used
A5: Insurance: per unit ($) | B5: 200 | C5: LAAA benchmark = (units x $200) + (gross SF x $1.00)
A6: Insurance: per gross SF ($) | B6: 1
A7: Repairs & maintenance per unit, pre-1990 ($/yr) | B7: 1200
A8: Repairs & maintenance per unit, 1990+ ($/yr) | B8: 800
A9: Utilities per unit, LA City ($/yr) | B9: 1500 | C9: Owner-paid water/sewer/trash/common electric+gas (LA Sanitation bundles trash)
A10: Utilities per unit, Santa Monica ($/yr) | B10: 1800 | C10: Separate trash hauler, higher water rates
A11: Utilities per unit, Beverly Hills / WeHo / Culver ($/yr) | B11: 1600
A12: Contract services per unit ($/yr) | B12: 400 | C12: Landscaping, pest, common-area cleaning
A13: Admin / legal / licenses / rent registration per unit ($/yr) | B13: 250 | C13: Includes RSO/rent-board fees, business license, bookkeeping
A14: Replacement reserves per unit ($/yr) | B14: 300
A15: Property tax rate: Los Angeles City | B15: 0.0125 | C15: Ad valorem + direct assessments, reassessed at purchase price
A16: Property tax rate: Santa Monica | B16: 0.0115
A17: Property tax rate: Beverly Hills | B17: 0.0115
A18: Property tax rate: West Hollywood | B18: 0.012
A19: Property tax rate: Culver City | B19: 0.012
A20: Financing: max LTV | B20: 0.6
A21: Financing: min DCR on LAAA NOI | B21: 1.25 | C21: Loan = lesser of LTV loan and DCR-sized loan
A22: Financing: interest rate | B22: 0.0625
A23: Financing: amortization (years) | B23: 30
A24: OM "light" threshold: LAAA total exceeds OM total by more than | B24: 0.05 | C24: Flags OM EXPENSES LIGHT on the deal tab and Master List
A26: Rent-allocation weights when only GRM is published (relative to 1 Bd)
A27: Studio | B27: 0.7
A28: 1 Bd | B28: 1
A29: 2 Bd | B29: 1.35
A30: 3 Bd | B30: 1.75
A32: Estimated in-place rents when NOTHING is published (orange cells on deal tabs)
A33: Coastal (SM / Venice / WeHo / BH): Studio | B33: 1900
A34: Coastal: 1 Bd | B34: 2400
A35: Coastal: 2 Bd | B35: 3200
A36: Coastal: 3 Bd | B36: 4200
A37: West LA / Palms / Culver: Studio | B37: 1750
A38: West LA / Palms / Culver: 1 Bd | B38: 2200
A39: West LA / Palms / Culver: 2 Bd | B39: 2900
A40: West LA / Palms / Culver: 3 Bd | B40: 3800

Sheet 08 1811 S Bentley Ave
A1: 1811 S Bentley Ave (Brazilia Apts)
A2: Los Angeles, CA 90025 | West LA / Sawtelle
A3: LoopNet listing | B3: Data pulled 9/17/2026 from LoopNet public listing + rent roll and expenses read from the listing broker's OM (Lyon Stahl / Serhant / Taksa, rent roll 9/1/2026)
A4: NOTE: | OM: Rent roll cross-check OK: 15 unit rents sum to $47,128/mo vs OM $47,127 (rounding); x12 = $565,536 vs OM $565,525 annual (0.002%).; Expense line items sum to $188,808, not the OM's stated total of $191,916 (short $3,108, 1.6%). NOI of $359,435 is computed off the $191,916 total; recomputed on the li
A6: PROPERTY
A7: Units | B7: 15
A8: Gross building SF | B8: 16568
A9: Lot SF | B9: 11761
A10: Lot acres | B10: 0.27
A11: Year built | B11: 1964 | C11: per Filip 9/17/2026 (LoopNet did not publish)
A12: Stories | B12: 3
A13: Zoning | B13: LAR3
A14: Occupancy per listing | B14: 100%
A15: APN | B15: 4323-021-022
A16: Assessed value (current) | B16: 5866611
A17: Listing broker(s) | B17: Jake Glaser
A18: Date on market | B18: 8/25/2026
A19: Listing last updated | B19: 9/16/2026
A21: PRICING
A22: Asking price | B22: 6350000
A23: Price per unit | B23: =IFERROR(B22/B7,"") -> 423333.33
A24: Price per gross SF | B24: =IFERROR(B22/B8,"") -> 383.26895
A25: OM / listing cap rate (as published) | B25: 0.0566
A26: OM / listing GRM (as published) | B26: 11.23
A28: UNIT MIX & SCHEDULED RENT
A29: Unit type | B29: # Units | C29: Avg rent / mo | D29: Monthly total | E29: Annual | F29: Rent source
A30: 1 Bd / 1 Ba [Unit 304, Non-RSO; at market ($2,900)] | B30: 1 | C30: 2900 | D30: =B30*C30 -> 2900 | E30: =D30*12 -> 34800 | F30: OM rent roll, current in-place rents (OM rent roll 9/1/2026)
A31: 2 Bd / 1 Ba [Unit 204, RSO; market $3,100] | B31: 1 | C31: 2648 | D31: =B31*C31 -> 2648 | E31: =D31*12 -> 31776 | F31: OM rent roll, current in-place rents (OM rent roll 9/1/2026)
A32: 2 Bd / 2 Ba [Units 100,101,102,103,200,203,303; rents $2,131 to $3,345 (s] | B32: 7 | C32: 2699 | D32: =B32*C32 -> 18893 | E32: =D32*12 -> 226716 | F32: OM rent roll, current in-place rents (OM rent roll 9/1/2026)
A33: 3 Bd / 2 Ba [Units 201,202,205,301,302,305; rents $3,531 to $3,952 (sum $] | B33: 6 | C33: 3780 | D33: =B33*C33 -> 22680 | E33: =D33*12 -> 272160 | F33: OM rent roll, current in-place rents (OM rent roll 9/1/2026)
A34: Total / weighted avg | B34: =SUM(B30:B33) -> 15 | C34: =IFERROR(D34/B34,"") -> 3141.4 | D34: =SUM(D30:D33) -> 47121 | E34: =SUM(E30:E33) -> 565452
A36: INCOME
B37: OM as presented | C37: LAAA underwritten | F37: Basis / note
A38: Scheduled gross rent | B38: 565525 | C38: =E34 -> 565452 | F38: OM column: OM stated current scheduled rent (OM rent roll 9/1/2026); LAAA column: OM rent roll by unit type
A39: Other income (laundry, parking, RUBS) | B39: 2791 | C39: 2791
A40: Gross scheduled income | B40: =B38+B39 -> 568316 | C40: =C38+C39 -> 568243
A41: Vacancy & credit loss | B41: =-B38*0.03 -> -16965.75 | C41: =-C38*Assumptions!$B$3 -> -16963.56 | F41: OM 3.0%; LAAA per Assumptions
A42: Effective gross income | B42: =B40+B41 -> 551350.25 | C42: =C40+C41 -> 551279.44
A44: OPERATING EXPENSES
A45: Expense line | B45: OM as presented | C45: LAAA benchmark | D45: LAAA underwritten | E45: Delta vs OM | F45: Basis / note
A46: Property taxes (reassessed at price) | B46: 75399 | C46: =B22*Assumptions!$B$15 -> 79375 | D46: =C46 -> 79375 | E46: =IF(ISNUMBER(B46),D46-B46,"") -> 3976 | F46: Los Angeles rate x asking price; always reassessed, never MAX
A47: Insurance | B47: 19527 | C47: =B7*Assumptions!$B$5+B8*Assumptions!$B$6 -> 19568 | D47: =IF(ISNUMBER(B47),MAX(B47,C47),C47) -> 19568 | E47: =IF(ISNUMBER(B47),D47-B47,"") -> 41 | F47: LAAA benchmark (units x $200) + (SF x $1.00)
A48: Management | B48: 22054 | C48: =C42*Assumptions!$B$4 -> 27563.972 | D48: =IF(ISNUMBER(B48),MAX(B48,C48),C48) -> 27563.972 | E48: =IF(ISNUMBER(B48),D48-B48,"") -> 5509.972 | F48: % of LAAA EGI
A49: Repairs & maintenance | B49: 22500 | C49: =B7*Assumptions!$B$7 -> 18000 | D49: =IF(ISNUMBER(B49),MAX(B49,C49),C49) -> 22500 | E49: =IF(ISNUMBER(B49),D49-B49,"") -> 0 | F49: per unit, by vintage
A50: Utilities (water/sewer/trash/common electric & gas) | B50: 28692 | C50: =B7*Assumptions!$B$9 -> 22500 | D50: =IF(ISNUMBER(B50),MAX(B50,C50),C50) -> 28692 | E50: =IF(ISNUMBER(B50),D50-B50,"") -> 0 | F50: per unit, by city; OM utilities + water/sewer + gas/electric + trash combined
A51: Contract services (landscape, pest, cleaning) | B51: 5646 | C51: =B7*Assumptions!$B$12 -> 6000 | D51: =IF(ISNUMBER(B51),MAX(B51,C51),C51) -> 6000 | E51: =IF(ISNUMBER(B51),D51-B51,"") -> 354 | F51: per unit
A52: Admin / legal / licenses / rent registration / other OM items | B52: 12848 | C52: =B7*Assumptions!$B$13 -> 3750 | D52: =IF(ISNUMBER(B52),MAX(B52,C52),C52) -> 12848 | E52: =IF(ISNUMBER(B52),D52-B52,"") -> 0 | F52: OM other items: Direct Assessments (2026 actual) 2,554; Maintenance Supplies (2026 annualized) 2,935; Utilities - Telephone (2026 annualized) 767; Elevator (2026 annualized) 2,724; Cleaning & Other Se
A53: Replacement reserves | B53: 5250 | C53: =B7*Assumptions!$B$14 -> 4500 | D53: =IF(ISNUMBER(B53),MAX(B53,C53),C53) -> 5250 | E53: =IF(ISNUMBER(B53),D53-B53,"") -> 0 | F53: per unit
A54: Total operating expenses | B54: =SUM(B46:B53) -> 191916 | C54: =SUM(C46:C53) -> 181256.97 | D54: =SUM(D46:D53) -> 201796.97 | E54: =IF(ISNUMBER(B54),D54-B54,"") -> 9880.972 | F54: OM line items from OM (OM rent roll 9/1/2026); basis: OM 'Current' column of the Pro Forma Annual Operating Expenses page. Mixed basis: taxes projected at 1.187% x sale price, management 4.0% x GOI (projected), insurance $1.18/GSF (labeled actual), R&M $1,500/unit and reserves $350/unit projected; direct assessments and all utility/service lines are 2026 actual/annualized. gas_electric is gas only (no electric line). utilities key left null because the OM breaks utilities out by line.; OM total 191,916
A55: Expenses per unit | B55: =IFERROR(B54/B7,"") -> 12794.4 | C55: =IFERROR(C54/B7,"") -> 12083.798 | D55: =IFERROR(D54/B7,"") -> 13453.131
A56: Expenses as % of EGI | B56: =IFERROR(B54/B42,"") -> 0.34808364 | C56: =IFERROR(C54/C42,"") -> 0.32879327 | D56: =IF(C38>0,IFERROR(D54/C42,""),"") -> 0.36605206
A57: OM expense test | B57: =IF(ISNUMBER(B54),IF(D54>B54*(1+Assumptions!$B$24),"OM EXPENSES LIGHT","OM expenses reasonable"),"OM expenses not published") -> OM EXPENSES LIGHT
A59: NOI & RETURNS
B60: OM as presented | C60: LAAA underwritten | F60: Basis / note
A61: Net operating income | B61: =B42-B54 -> 359434.25 | C61: =IF(C38>0,C42-D54,"") -> 349482.47 | F61: OM states NOI 359,435 / cap 5.66
A62: Cap rate on asking price | B62: =IFERROR(B61/B22,"") -> 0.056603819 | C62: =IF(C61="","",IFERROR(C61/B22,"")) -> 0.055036609 | F62: OM column recomputed from OM figures; compare to published cap above
A63: GRM (price / scheduled rent) | B63: =IFERROR(B22/B38,"") -> 11.228504 | C63: =IF(C38>0,IFERROR(B22/C38,""),"") -> 11.229954
A64: NOI per unit | B64: =IFERROR(B61/B7,"") -> 23962.283 | C64: =IF(C61="","",IFERROR(C61/B7,"")) -> 23298.831
A66: FINANCING (illustrative, on LAAA NOI)
A67: LTV loan | B67: =IFERROR(B22*Assumptions!$B$20,"") -> 3810000
A68: DCR-sized loan | B68: =IF(C61="","",IFERROR(PV(Assumptions!$B$22/12,Assumptions!$B$23*12,-C61/Assumptions!$B$21/12),"")) -> 3784015
A69: Loan amount (lesser of) | B69: =IFERROR(MIN(B67,B68),"") -> 3784015
A70: Down payment | B70: =IFERROR(B22-B69,"") -> 2565985
A71: Annual debt service | B71: =IFERROR(-PMT(Assumptions!$B$22/12,Assumptions!$B$23*12,B69)*12,"") -> 279585.97
A72: DCR | B72: =IFERROR(C61/B71,"") -> 1.25
A73: Cash flow after debt service | B73: =IFERROR(C61-B71,"") -> 69896.494
A74: Cash-on-cash return | B74: =IFERROR(B73/B70,"") -> 0.027239634
A76: Legend: yellow = published input, orange = estimated (nothing published), grey = LAAA underwritten (MAX of OM line and benchmark; taxes always reassessed).
