Workbook

Sheet Assumptions
A1: LAAA UNDERWRITING BENCHMARKS (edit here; every deal tab reads these)
A3: Vacancy & credit loss (% of GSI) | B3: 0.03 | C3: Standard LA practice; vacant units carried at asking rent inside scheduled GSR
A4: Management fee (% of EGI) | B4: 0.05 | C4: Deal-by-deal agent choice; 5% default, MAX(OM, benchmark) used
A5: Insurance: per unit ($) | B5: 200 | C5: LAAA benchmark = (units x $200) + (gross SF x $1.00)
A6: Insurance: per gross SF ($) | B6: 1
A7: Repairs & maintenance per unit, pre-1990 ($/yr) | B7: 1200
A8: Repairs & maintenance per unit, 1990+ ($/yr) | B8: 800
A9: Utilities per unit, LA City ($/yr) | B9: 1500 | C9: Owner-paid water/sewer/trash/common electric+gas (LA Sanitation bundles trash)
A10: Utilities per unit, Santa Monica ($/yr) | B10: 1800 | C10: Separate trash hauler, higher water rates
A11: Utilities per unit, Beverly Hills / WeHo / Culver ($/yr) | B11: 1600
A12: Contract services per unit ($/yr) | B12: 400 | C12: Landscaping, pest, common-area cleaning
A13: Admin / legal / licenses / rent registration per unit ($/yr) | B13: 250 | C13: Includes RSO/rent-board fees, business license, bookkeeping
A14: Replacement reserves per unit ($/yr) | B14: 300
A15: Property tax rate: Los Angeles City | B15: 0.0125 | C15: Ad valorem + direct assessments, reassessed at purchase price
A16: Property tax rate: Santa Monica | B16: 0.0115
A17: Property tax rate: Beverly Hills | B17: 0.0115
A18: Property tax rate: West Hollywood | B18: 0.012
A19: Property tax rate: Culver City | B19: 0.012
A20: Financing: max LTV | B20: 0.6
A21: Financing: min DCR on LAAA NOI | B21: 1.25 | C21: Loan = lesser of LTV loan and DCR-sized loan
A22: Financing: interest rate | B22: 0.0625
A23: Financing: amortization (years) | B23: 30
A24: OM "light" threshold: LAAA total exceeds OM total by more than | B24: 0.05 | C24: Flags OM EXPENSES LIGHT on the deal tab and Master List
A26: Rent-allocation weights when only GRM is published (relative to 1 Bd)
A27: Studio | B27: 0.7
A28: 1 Bd | B28: 1
A29: 2 Bd | B29: 1.35
A30: 3 Bd | B30: 1.75
A32: Estimated in-place rents when NOTHING is published (orange cells on deal tabs)
A33: Coastal (SM / Venice / WeHo / BH): Studio | B33: 1900
A34: Coastal: 1 Bd | B34: 2400
A35: Coastal: 2 Bd | B35: 3200
A36: Coastal: 3 Bd | B36: 4200
A37: West LA / Palms / Culver: Studio | B37: 1750
A38: West LA / Palms / Culver: 1 Bd | B38: 2200
A39: West LA / Palms / Culver: 2 Bd | B39: 2900
A40: West LA / Palms / Culver: 3 Bd | B40: 3800

Sheet 11 440 Raymond Ave
A1: 440 Raymond Ave
A2: Santa Monica, CA 90405 | Santa Monica
A3: LoopNet listing | B3: Data pulled 9/17/2026 from LoopNet public listing + LAAA OM extraction (July 2026 intake)
A6: PROPERTY
A7: Units | B7: 20
A8: Gross building SF | B8: 15820
A9: Lot SF | B9: 13939
A10: Lot acres | B10: 0.32
A11: Year built | B11: 1969
A12: Stories | B12: 2
A13: Zoning | B13: R3, Santa Monica - OP2
A14: Occupancy per listing | B14: 95%
A15: APN | B15: 4287-020-031
A16: Assessed value (current) | B16: 2259813
A17: Listing broker(s) | B17: Benjamin Hsiang, Don Favia
A18: Date on market | B18: 6/16/2026
A19: Listing last updated | B19: 8/14/2026
A21: PRICING
A22: Asking price | B22: 7750000
A23: Price per unit | B23: =IFERROR(B22/B7,"") -> 387500
A24: Price per gross SF | B24: =IFERROR(B22/B8,"") -> 489.88622
A25: OM / listing cap rate (as published) | B25: 0.0557
A26: OM / listing GRM (as published) | B26: 12.15
A28: UNIT MIX & SCHEDULED RENT
A29: Unit type | B29: # Units | C29: Avg rent / mo | D29: Monthly total | E29: Annual | F29: Rent source
A30: 2 Bd / 2 Ba | B30: 8 | C30: 2927 | D30: =B30*C30 -> 23416 | E30: =D30*12 -> 280992 | F30: LoopNet published avg rent by unit type
A31: 1 Bd / 1 Ba | B31: 12 | C31: 2425 | D31: =B31*C31 -> 29100 | E31: =D31*12 -> 349200 | F31: LoopNet published avg rent by unit type
A32: Total / weighted avg | B32: =SUM(B30:B31) -> 20 | C32: =IFERROR(D32/B32,"") -> 2625.8 | D32: =SUM(D30:D31) -> 52516 | E32: =SUM(E30:E31) -> 630192
A34: INCOME
B35: OM as presented | C35: LAAA underwritten | F35: Basis / note
A36: Scheduled gross rent | B36: 631196 | C36: =E32 -> 630192 | F36: OM column: OM rent roll
A37: Other income (laundry, parking, RUBS) | B37: 7740 | C37: 7740
A38: Gross scheduled income | B38: =B36+B37 -> 638936 | C38: =C36+C37 -> 637932
A39: Vacancy & credit loss | B39: =-B36*0.03 -> -18935.88 | C39: =-C36*Assumptions!$B$3 -> -18905.76 | F39: OM 3.0% (OM figure if extracted, else 3% assumed); LAAA per Assumptions
A40: Effective gross income | B40: =B38+B39 -> 620000.12 | C40: =C38+C39 -> 619026.24
A42: OPERATING EXPENSES
A43: Expense line | B43: OM as presented | C43: LAAA benchmark | D43: LAAA underwritten | E43: Delta vs OM | F43: Basis / note
A44: Property taxes (reassessed at price) | B44: 93000 | C44: =B22*Assumptions!$B$16 -> 89125 | D44: =C44 -> 89125 | E44: =IF(ISNUMBER(B44),D44-B44,"") -> -3875 | F44: Santa Monica rate x asking price; always reassessed, never MAX
A45: Insurance | B45: 15820 | C45: =B7*Assumptions!$B$5+B8*Assumptions!$B$6 -> 19820 | D45: =IF(ISNUMBER(B45),MAX(B45,C45),C45) -> 19820 | E45: =IF(ISNUMBER(B45),D45-B45,"") -> 4000 | F45: LAAA benchmark (units x $200) + (SF x $1.00)
A46: Management | B46: 24388 | C46: =C40*Assumptions!$B$4 -> 30951.312 | D46: =IF(ISNUMBER(B46),MAX(B46,C46),C46) -> 30951.312 | E46: =IF(ISNUMBER(B46),D46-B46,"") -> 6563.312 | F46: % of LAAA EGI
A47: Repairs & maintenance | B47: 22000 | C47: =B7*Assumptions!$B$7 -> 24000 | D47: =IF(ISNUMBER(B47),MAX(B47,C47),C47) -> 24000 | E47: =IF(ISNUMBER(B47),D47-B47,"") -> 2000 | F47: per unit, by vintage
A48: Utilities (water/sewer/trash/common electric & gas) | B48: 20000 | C48: =B7*Assumptions!$B$10 -> 36000 | D48: =IF(ISNUMBER(B48),MAX(B48,C48),C48) -> 36000 | E48: =IF(ISNUMBER(B48),D48-B48,"") -> 16000 | F48: per unit, by city
A49: Contract services (landscape, pest, cleaning) | B49: 2400 | C49: =B7*Assumptions!$B$12 -> 8000 | D49: =IF(ISNUMBER(B49),MAX(B49,C49),C49) -> 8000 | E49: =IF(ISNUMBER(B49),D49-B49,"") -> 5600 | F49: per unit
A50: Admin / legal / licenses / rent registration / other OM items | B50: 9180 | C50: =B7*Assumptions!$B$13 -> 5000 | D50: =IF(ISNUMBER(B50),MAX(B50,C50),C50) -> 9180 | E50: =IF(ISNUMBER(B50),D50-B50,"") -> 0 | F50: OM other items: Rent Control Fees 4,560; Manager/Keyholder 4,620
A51: Replacement reserves | C51: =B7*Assumptions!$B$14 -> 6000 | D51: =IF(ISNUMBER(B51),MAX(B51,C51),C51) -> 6000 | E51: =IF(ISNUMBER(B51),D51-B51,"") | F51: per unit
A52: Total operating expenses | B52: =SUM(B44:B51) -> 186788 | C52: =SUM(C44:C51) -> 218896.31 | D52: =SUM(D44:D51) -> 223076.31 | E52: =IF(ISNUMBER(B52),D52-B52,"") -> 36288.312 | F52: OM claimed total 186,788 (lines mapped from OM extraction)
A53: Expenses per unit | B53: =IFERROR(B52/B7,"") -> 9339.4 | C53: =IFERROR(C52/B7,"") -> 10944.816 | D53: =IFERROR(D52/B7,"") -> 11153.816
A54: Expenses as % of EGI | B54: =IFERROR(B52/B40,"") -> 0.30127091 | C54: =IFERROR(C52/C40,"") -> 0.35361395 | D54: =IF(C36>0,IFERROR(D52/C40,""),"") -> 0.36036649
A55: OM expense test | B55: =IF(ISNUMBER(B52),IF(D52>B52*(1+Assumptions!$B$24),"OM EXPENSES LIGHT","OM expenses reasonable"),"OM expenses not published") -> OM EXPENSES LIGHT
A57: NOI & RETURNS
B58: OM as presented | C58: LAAA underwritten | F58: Basis / note
A59: Net operating income | B59: =B40-B52 -> 433212.12 | C59: =IF(C36>0,C40-D52,"") -> 395949.93
A60: Cap rate on asking price | B60: =IFERROR(B59/B22,"") -> 0.055898338 | C60: =IF(C59="","",IFERROR(C59/B22,"")) -> 0.051090313 | F60: OM column recomputed from OM figures; compare to published cap above
A61: GRM (price / scheduled rent) | B61: =IFERROR(B22/B36,"") -> 12.278278 | C61: =IF(C36>0,IFERROR(B22/C36,""),"") -> 12.297839
A62: NOI per unit | B62: =IFERROR(B59/B7,"") -> 21660.606 | C62: =IF(C59="","",IFERROR(C59/B7,"")) -> 19797.496
A64: FINANCING (illustrative, on LAAA NOI)
A65: LTV loan | B65: =IFERROR(B22*Assumptions!$B$20,"") -> 4650000
A66: DCR-sized loan | B66: =IF(C59="","",IFERROR(PV(Assumptions!$B$22/12,Assumptions!$B$23*12,-C59/Assumptions!$B$21/12),"")) -> 4287140.6
A67: Loan amount (lesser of) | B67: =IFERROR(MIN(B65,B66),"") -> 4287140.6
A68: Down payment | B68: =IFERROR(B22-B67,"") -> 3462859.4
A69: Annual debt service | B69: =IFERROR(-PMT(Assumptions!$B$22/12,Assumptions!$B$23*12,B67)*12,"") -> 316759.94
A70: DCR | B70: =IFERROR(C59/B69,"") -> 1.25
A71: Cash flow after debt service | B71: =IFERROR(C59-B69,"") -> 79189.986
A72: Cash-on-cash return | B72: =IFERROR(B71/B68,"") -> 0.02286838
A74: Legend: yellow = published input, orange = estimated (nothing published), grey = LAAA underwritten (MAX of OM line and benchmark; taxes always reassessed).
