Workbook

Sheet Assumptions
A1: LAAA UNDERWRITING BENCHMARKS (edit here; every deal tab reads these)
A3: Vacancy & credit loss (% of GSI) | B3: 0.03 | C3: Standard LA practice; vacant units carried at asking rent inside scheduled GSR
A4: Management fee (% of EGI) | B4: 0.05 | C4: Deal-by-deal agent choice; 5% default, MAX(OM, benchmark) used
A5: Insurance: per unit ($) | B5: 200 | C5: LAAA benchmark = (units x $200) + (gross SF x $1.00)
A6: Insurance: per gross SF ($) | B6: 1
A7: Repairs & maintenance per unit, pre-1990 ($/yr) | B7: 1200
A8: Repairs & maintenance per unit, 1990+ ($/yr) | B8: 800
A9: Utilities per unit, LA City ($/yr) | B9: 1500 | C9: Owner-paid water/sewer/trash/common electric+gas (LA Sanitation bundles trash)
A10: Utilities per unit, Santa Monica ($/yr) | B10: 1800 | C10: Separate trash hauler, higher water rates
A11: Utilities per unit, Beverly Hills / WeHo / Culver ($/yr) | B11: 1600
A12: Contract services per unit ($/yr) | B12: 400 | C12: Landscaping, pest, common-area cleaning
A13: Admin / legal / licenses / rent registration per unit ($/yr) | B13: 250 | C13: Includes RSO/rent-board fees, business license, bookkeeping
A14: Replacement reserves per unit ($/yr) | B14: 300
A15: Property tax rate: Los Angeles City | B15: 0.0125 | C15: Ad valorem + direct assessments, reassessed at purchase price
A16: Property tax rate: Santa Monica | B16: 0.0115
A17: Property tax rate: Beverly Hills | B17: 0.0115
A18: Property tax rate: West Hollywood | B18: 0.012
A19: Property tax rate: Culver City | B19: 0.012
A20: Financing: max LTV | B20: 0.6
A21: Financing: min DCR on LAAA NOI | B21: 1.25 | C21: Loan = lesser of LTV loan and DCR-sized loan
A22: Financing: interest rate | B22: 0.0625
A23: Financing: amortization (years) | B23: 30
A24: OM "light" threshold: LAAA total exceeds OM total by more than | B24: 0.05 | C24: Flags OM EXPENSES LIGHT on the deal tab and Master List
A26: Rent-allocation weights when only GRM is published (relative to 1 Bd)
A27: Studio | B27: 0.7
A28: 1 Bd | B28: 1
A29: 2 Bd | B29: 1.35
A30: 3 Bd | B30: 1.75
A32: Estimated in-place rents when NOTHING is published (orange cells on deal tabs)
A33: Coastal (SM / Venice / WeHo / BH): Studio | B33: 1900
A34: Coastal: 1 Bd | B34: 2400
A35: Coastal: 2 Bd | B35: 3200
A36: Coastal: 3 Bd | B36: 4200
A37: West LA / Palms / Culver: Studio | B37: 1750
A38: West LA / Palms / Culver: 1 Bd | B38: 2200
A39: West LA / Palms / Culver: 2 Bd | B39: 2900
A40: West LA / Palms / Culver: 3 Bd | B40: 3800

Sheet 15 1041 S Corning St
A1: 1041 S Corning St
A2: Los Angeles, CA 90035 | Pico-Robertson / Beverlywood
A3: LoopNet listing | B3: Data pulled 9/17/2026 from LoopNet public listing
A4: NOTE: UNDER CONTRACT per Filip 9/17/26 (confirm which Corning listing). 15 units plus one non-conforming unit per listing
A6: PROPERTY
A7: Units | B7: 15
A8: Gross building SF | B8: 16234
A9: Lot SF | B9: 12197
A10: Lot acres | B10: 0.28
A11: Year built | B11: 1962
A12: Stories | B12: 3
A13: Zoning | B13: R3-1, Los Angeles
A14: Occupancy per listing
A15: APN | B15: 4332-025-030
A16: Assessed value (current) | B16: 2625924
A17: Listing broker(s) | B17: Neema Ahadian, Jeffrey Estrada
A18: Date on market | B18: 7/28/2026
A19: Listing last updated | B19: 8/26/2026
A21: PRICING
A22: Asking price | B22: 4700000
A23: Price per unit | B23: =IFERROR(B22/B7,"") -> 313333.33
A24: Price per gross SF | B24: =IFERROR(B22/B8,"") -> 289.51583
A25: OM / listing cap rate (as published) | B25: 0.055
A26: OM / listing GRM (as published) | B26: 10.48
A28: UNIT MIX & SCHEDULED RENT
A29: Unit type | B29: # Units | C29: Avg rent / mo | D29: Monthly total | E29: Annual | F29: Rent source
A30: 1 Bd / 1 Ba (~750 SF) | B30: 2 | C30: 1873 | D30: =B30*C30 -> 3746 | E30: =D30*12 -> 44952 | F30: Allocated from published GRM (price / GRM) using LAAA bed weights
A31: 2 Bd / 2 Ba (~950 SF) | B31: 12 | C31: 2529 | D31: =B31*C31 -> 30348 | E31: =D31*12 -> 364176 | F31: Allocated from published GRM (price / GRM) using LAAA bed weights
A32: 3 Bd / 3 Ba (~1200 SF) | B32: 1 | C32: 3278 | D32: =B32*C32 -> 3278 | E32: =D32*12 -> 39336 | F32: Allocated from published GRM (price / GRM) using LAAA bed weights
A33: Total / weighted avg | B33: =SUM(B30:B32) -> 15 | C33: =IFERROR(D33/B33,"") -> 2491.4667 | D33: =SUM(D30:D32) -> 37372 | E33: =SUM(E30:E32) -> 448464
A35: INCOME
B36: OM as presented | C36: LAAA underwritten | F36: Basis / note
A37: Scheduled gross rent | B37: 448473.28 | C37: =E33 -> 448464 | F37: OM column: price / published GRM
A38: Other income (laundry, parking, RUBS) | B38: 0 | C38: 0
A39: Gross scheduled income | B39: =B37+B38 -> 448473.28 | C39: =C37+C38 -> 448464
A40: Vacancy & credit loss | B40: =-B37*0.03 -> -13454.198 | C40: =-C37*Assumptions!$B$3 -> -13453.92 | F40: OM 3.0% (OM figure if extracted, else 3% assumed); LAAA per Assumptions
A41: Effective gross income | B41: =B39+B40 -> 435019.08 | C41: =C39+C40 -> 435010.08
A43: OPERATING EXPENSES
A44: Expense line | B44: OM as presented | C44: LAAA benchmark | D44: LAAA underwritten | E44: Delta vs OM | F44: Basis / note
A45: Property taxes (reassessed at price) | C45: =B22*Assumptions!$B$15 -> 58750 | D45: =C45 -> 58750 | E45: =IF(ISNUMBER(B45),D45-B45,"") | F45: Los Angeles rate x asking price; always reassessed, never MAX
A46: Insurance | C46: =B7*Assumptions!$B$5+B8*Assumptions!$B$6 -> 19234 | D46: =IF(ISNUMBER(B46),MAX(B46,C46),C46) -> 19234 | E46: =IF(ISNUMBER(B46),D46-B46,"") | F46: LAAA benchmark (units x $200) + (SF x $1.00)
A47: Management | C47: =C41*Assumptions!$B$4 -> 21750.504 | D47: =IF(ISNUMBER(B47),MAX(B47,C47),C47) -> 21750.504 | E47: =IF(ISNUMBER(B47),D47-B47,"") | F47: % of LAAA EGI
A48: Repairs & maintenance | C48: =B7*Assumptions!$B$7 -> 18000 | D48: =IF(ISNUMBER(B48),MAX(B48,C48),C48) -> 18000 | E48: =IF(ISNUMBER(B48),D48-B48,"") | F48: per unit, by vintage
A49: Utilities (water/sewer/trash/common electric & gas) | C49: =B7*Assumptions!$B$9 -> 22500 | D49: =IF(ISNUMBER(B49),MAX(B49,C49),C49) -> 22500 | E49: =IF(ISNUMBER(B49),D49-B49,"") | F49: per unit, by city
A50: Contract services (landscape, pest, cleaning) | C50: =B7*Assumptions!$B$12 -> 6000 | D50: =IF(ISNUMBER(B50),MAX(B50,C50),C50) -> 6000 | E50: =IF(ISNUMBER(B50),D50-B50,"") | F50: per unit
A51: Admin / legal / licenses / rent registration | C51: =B7*Assumptions!$B$13 -> 3750 | D51: =IF(ISNUMBER(B51),MAX(B51,C51),C51) -> 3750 | E51: =IF(ISNUMBER(B51),D51-B51,"") | F51: per unit; OM "other" items land here
A52: Replacement reserves | C52: =B7*Assumptions!$B$14 -> 4500 | D52: =IF(ISNUMBER(B52),MAX(B52,C52),C52) -> 4500 | E52: =IF(ISNUMBER(B52),D52-B52,"") | F52: per unit
A53: Total operating expenses | B53: =B41-B22*B25 -> 176519.08 | C53: =SUM(C45:C52) -> 154484.5 | D53: =SUM(D45:D52) -> 154484.5 | E53: =IF(ISNUMBER(B53),D53-B53,"") -> -22034.58 | F53: OM line items not published. OM total IMPLIED = OM EGI - (price x published cap)
A54: Expenses per unit | B54: =IFERROR(B53/B7,"") -> 11767.939 | C54: =IFERROR(C53/B7,"") -> 10298.967 | D54: =IFERROR(D53/B7,"") -> 10298.967
A55: Expenses as % of EGI | B55: =IFERROR(B53/B41,"") -> 0.4057732 | C55: =IFERROR(C53/C41,"") -> 0.35512856 | D55: =IF(C37>0,IFERROR(D53/C41,""),"") -> 0.35512856
A56: OM expense test | B56: =IF(ISNUMBER(B53),IF(D53>B53*(1+Assumptions!$B$24),"OM EXPENSES LIGHT","OM expenses reasonable"),"OM expenses not published") -> OM expenses reasonable
A58: NOI & RETURNS
B59: OM as presented | C59: LAAA underwritten | F59: Basis / note
A60: Net operating income | B60: =B41-B53 -> 258500 | C60: =IF(C37>0,C41-D53,"") -> 280525.58
A61: Cap rate on asking price | B61: =IFERROR(B60/B22,"") -> 0.055 | C61: =IF(C60="","",IFERROR(C60/B22,"")) -> 0.059686293 | F61: OM column recomputed from OM figures; compare to published cap above
A62: GRM (price / scheduled rent) | B62: =IFERROR(B22/B37,"") -> 10.48 | C62: =IF(C37>0,IFERROR(B22/C37,""),"") -> 10.480217
A63: NOI per unit | B63: =IFERROR(B60/B7,"") -> 17233.333 | C63: =IF(C60="","",IFERROR(C60/B7,"")) -> 18701.705
A65: FINANCING (illustrative, on LAAA NOI)
A66: LTV loan | B66: =IFERROR(B22*Assumptions!$B$20,"") -> 2820000
A67: DCR-sized loan | B67: =IF(C60="","",IFERROR(PV(Assumptions!$B$22/12,Assumptions!$B$23*12,-C60/Assumptions!$B$21/12),"")) -> 3037385.5
A68: Loan amount (lesser of) | B68: =IFERROR(MIN(B66,B67),"") -> 2820000
A69: Down payment | B69: =IFERROR(B22-B68,"") -> 1880000
A70: Annual debt service | B70: =IFERROR(-PMT(Assumptions!$B$22/12,Assumptions!$B$23*12,B68)*12,"") -> 208358.7
A71: DCR | B71: =IFERROR(C60/B70,"") -> 1.3463588
A72: Cash flow after debt service | B72: =IFERROR(C60-B70,"") -> 72166.875
A73: Cash-on-cash return | B73: =IFERROR(B72/B69,"") -> 0.038386636
A75: Legend: yellow = published input, orange = estimated (nothing published), grey = LAAA underwritten (MAX of OM line and benchmark; taxes always reassessed).
