Workbook

Sheet Assumptions
A1: LAAA UNDERWRITING BENCHMARKS (edit here; every deal tab reads these)
A3: Vacancy & credit loss (% of GSI) | B3: 0.03 | C3: Standard LA practice; vacant units carried at asking rent inside scheduled GSR
A4: Management fee (% of EGI) | B4: 0.05 | C4: Deal-by-deal agent choice; 5% default, MAX(OM, benchmark) used
A5: Insurance: per unit ($) | B5: 200 | C5: LAAA benchmark = (units x $200) + (gross SF x $1.00)
A6: Insurance: per gross SF ($) | B6: 1
A7: Repairs & maintenance per unit, pre-1990 ($/yr) | B7: 1200
A8: Repairs & maintenance per unit, 1990+ ($/yr) | B8: 800
A9: Utilities per unit, LA City ($/yr) | B9: 1500 | C9: Owner-paid water/sewer/trash/common electric+gas (LA Sanitation bundles trash)
A10: Utilities per unit, Santa Monica ($/yr) | B10: 1800 | C10: Separate trash hauler, higher water rates
A11: Utilities per unit, Beverly Hills / WeHo / Culver ($/yr) | B11: 1600
A12: Contract services per unit ($/yr) | B12: 400 | C12: Landscaping, pest, common-area cleaning
A13: Admin / legal / licenses / rent registration per unit ($/yr) | B13: 250 | C13: Includes RSO/rent-board fees, business license, bookkeeping
A14: Replacement reserves per unit ($/yr) | B14: 300
A15: Property tax rate: Los Angeles City | B15: 0.0125 | C15: Ad valorem + direct assessments, reassessed at purchase price
A16: Property tax rate: Santa Monica | B16: 0.0115
A17: Property tax rate: Beverly Hills | B17: 0.0115
A18: Property tax rate: West Hollywood | B18: 0.012
A19: Property tax rate: Culver City | B19: 0.012
A20: Financing: max LTV | B20: 0.6
A21: Financing: min DCR on LAAA NOI | B21: 1.25 | C21: Loan = lesser of LTV loan and DCR-sized loan
A22: Financing: interest rate | B22: 0.0625
A23: Financing: amortization (years) | B23: 30
A24: OM "light" threshold: LAAA total exceeds OM total by more than | B24: 0.05 | C24: Flags OM EXPENSES LIGHT on the deal tab and Master List
A26: Rent-allocation weights when only GRM is published (relative to 1 Bd)
A27: Studio | B27: 0.7
A28: 1 Bd | B28: 1
A29: 2 Bd | B29: 1.35
A30: 3 Bd | B30: 1.75
A32: Estimated in-place rents when NOTHING is published (orange cells on deal tabs)
A33: Coastal (SM / Venice / WeHo / BH): Studio | B33: 1900
A34: Coastal: 1 Bd | B34: 2400
A35: Coastal: 2 Bd | B35: 3200
A36: Coastal: 3 Bd | B36: 4200
A37: West LA / Palms / Culver: Studio | B37: 1750
A38: West LA / Palms / Culver: 1 Bd | B38: 2200
A39: West LA / Palms / Culver: 2 Bd | B39: 2900
A40: West LA / Palms / Culver: 3 Bd | B40: 3800

Sheet 17 900 N Orange Grove Ave
A1: 900 N Orange Grove Ave
A2: West Hollywood, CA 90046 | West Hollywood
A3: LoopNet listing | B3: Data pulled 9/17/2026 from LoopNet public listing + rent roll and expenses read from the listing broker's OM (Marcus & Millichap, Aug 2026)
A4: NOTE: First sale in 38 years | OM: Unit 21 (1 Bd / 1 Ba) is vacant; OM asking rent $2,300 used as its current rent, per OM convention (OM totals include it in scheduled rent).; Cross-check: sum of 20 unit rents = $33,311/mo ($399,732/yr) vs OM stated $33,310/mo and $399,722/yr GPR; difference is rounding, well within 1%.; Rent roll f | OM: Unit 21 (1 Bd / 1 Ba) is vacant; OM asking rent $2,300 used as its current rent, per OM convention (OM totals include it in scheduled rent).; Cross-check: sum of 20 unit rents = $33,311/mo ($399,732/yr) vs OM stated $33,310/mo and $399,722/yr GPR; difference is rounding, well within 1%.; Rent roll f
A6: PROPERTY
A7: Units | B7: 20
A8: Gross building SF | B8: 14556
A9: Lot SF | B9: 12632
A10: Lot acres | B10: 0.29
A11: Year built | B11: 1957
A12: Stories | B12: 2
A13: Zoning | B13: WDR3C* - Restricted Density Multiple Dwelling
A14: Occupancy per listing
A15: APN | B15: 5530-026-019
A16: Assessed value (current) | B16: 3261097
A17: Listing broker(s) | B17: Jordan Asheghian, Tony Azzi
A18: Date on market | B18: 8/27/2026
A19: Listing last updated | B19: 8/31/2026
A21: PRICING
A22: Asking price | B22: 4150000
A23: Price per unit | B23: =IFERROR(B22/B7,"") -> 207500
A24: Price per gross SF | B24: =IFERROR(B22/B8,"") -> 285.1058
A25: OM / listing cap rate (as published) | B25: 0.0532
A26: OM / listing GRM (as published) | B26: 10.38
A28: UNIT MIX & SCHEDULED RENT
A29: Unit type | B29: # Units | C29: Avg rent / mo | D29: Monthly total | E29: Annual | F29: Rent source
A30: Studio / 1 Ba (~520 SF) [units 5, 6, 16, 17; range $833 to $1,575] | B30: 4 | C30: 1194 | D30: =B30*C30 -> 4776 | E30: =D30*12 -> 57312 | F30: OM rent roll, current in-place rents (OM Aug 2026)
A31: 1 Bd / 1 Ba (~720 SF) [units 1-3, 8-12, 14, 15, 19-21; unit 8 is 900 SF, rest 720 S] | B31: 13 | C31: 1622 | D31: =B31*C31 -> 21086 | E31: =D31*12 -> 253032 | F31: OM rent roll, current in-place rents (OM Aug 2026)
A32: 2 Bd / 1 Ba (~900 SF) [units 7, 18] | B32: 2 | C32: 2545 | D32: =B32*C32 -> 5090 | E32: =D32*12 -> 61080 | F32: OM rent roll, current in-place rents (OM Aug 2026)
A33: 2 Bd / 2 Ba (~900 SF) [unit 4] | B33: 1 | C33: 2363 | D33: =B33*C33 -> 2363 | E33: =D33*12 -> 28356 | F33: OM rent roll, current in-place rents (OM Aug 2026)
A34: Total / weighted avg | B34: =SUM(B30:B33) -> 20 | C34: =IFERROR(D34/B34,"") -> 1665.75 | D34: =SUM(D30:D33) -> 33315 | E34: =SUM(E30:E33) -> 399780
A36: INCOME
B37: OM as presented | C37: LAAA underwritten | F37: Basis / note
A38: Scheduled gross rent | B38: 399722 | C38: =E34 -> 399780 | F38: OM column: OM stated current scheduled rent (OM Aug 2026); LAAA column: OM rent roll by unit type
A39: Other income (laundry, parking, RUBS) | B39: 3000 | C39: 3000
A40: Gross scheduled income | B40: =B38+B39 -> 402722 | C40: =C38+C39 -> 402780
A41: Vacancy & credit loss | B41: =-B38*0.02 -> -7994.44 | C41: =-C38*Assumptions!$B$3 -> -11993.4 | F41: OM 2.0%; LAAA per Assumptions
A42: Effective gross income | B42: =B40+B41 -> 394727.56 | C42: =C40+C41 -> 390786.6
A44: OPERATING EXPENSES
A45: Expense line | B45: OM as presented | C45: LAAA benchmark | D45: LAAA underwritten | E45: Delta vs OM | F45: Basis / note
A46: Property taxes (reassessed at price) | B46: 48769 | C46: =B22*Assumptions!$B$18 -> 49800 | D46: =C46 -> 49800 | E46: =IF(ISNUMBER(B46),D46-B46,"") -> 1031 | F46: West Hollywood rate x asking price; always reassessed, never MAX
A47: Insurance | B47: 29521 | C47: =B7*Assumptions!$B$5+B8*Assumptions!$B$6 -> 18556 | D47: =IF(ISNUMBER(B47),MAX(B47,C47),C47) -> 29521 | E47: =IF(ISNUMBER(B47),D47-B47,"") -> 0 | F47: LAAA benchmark (units x $200) + (SF x $1.00)
A48: Management | B48: 15989 | C48: =C42*Assumptions!$B$4 -> 19539.33 | D48: =IF(ISNUMBER(B48),MAX(B48,C48),C48) -> 19539.33 | E48: =IF(ISNUMBER(B48),D48-B48,"") -> 3550.33 | F48: % of LAAA EGI
A49: Repairs & maintenance | B49: 20000 | C49: =B7*Assumptions!$B$7 -> 24000 | D49: =IF(ISNUMBER(B49),MAX(B49,C49),C49) -> 24000 | E49: =IF(ISNUMBER(B49),D49-B49,"") -> 4000 | F49: per unit, by vintage
A50: Utilities (water/sewer/trash/common electric & gas) | B50: 32789 | C50: =B7*Assumptions!$B$11 -> 32000 | D50: =IF(ISNUMBER(B50),MAX(B50,C50),C50) -> 32789 | E50: =IF(ISNUMBER(B50),D50-B50,"") -> 0 | F50: per unit, by city; OM utilities + water/sewer + gas/electric + trash combined
A51: Contract services (landscape, pest, cleaning) | B51: 6602 | C51: =B7*Assumptions!$B$12 -> 8000 | D51: =IF(ISNUMBER(B51),MAX(B51,C51),C51) -> 8000 | E51: =IF(ISNUMBER(B51),D51-B51,"") -> 1398 | F51: per unit
A52: Admin / legal / licenses / rent registration / other OM items | B52: 20400 | C52: =B7*Assumptions!$B$13 -> 5000 | D52: =IF(ISNUMBER(B52),MAX(B52,C52),C52) -> 20400 | E52: =IF(ISNUMBER(B52),D52-B52,"") -> 0 | F52: OM other items: On Site Manager 13,200; Pool 4,320; Rent Registration 2,880
A53: Replacement reserves | C53: =B7*Assumptions!$B$14 -> 6000 | D53: =IF(ISNUMBER(B53),MAX(B53,C53),C53) -> 6000 | E53: =IF(ISNUMBER(B53),D53-B53,"") | F53: per unit
A54: Total operating expenses | B54: =SUM(B46:B53) -> 174070 | C54: =SUM(C46:C53) -> 162895.33 | D54: =SUM(D46:D53) -> 190049.33 | E54: =IF(ISNUMBER(B54),D54-B54,"") -> 15979.33 | F54: OM line items from OM (OM Aug 2026); basis: OM 'Current' column on the Income and Expense page (p29) and Financial Overview (p30); taxes, R&M and off-site management are marked '*Estimated' by the OM (taxes = 1.1751% of list price; off-site management = 4.0% of GPR); other lines are presented as actuals. Utilities is one combined line (power, gas and water; water master metered, gas and electric separately metered). Pro forma column differs only in management ($22,502).; OM total 174,070
A55: Expenses per unit | B55: =IFERROR(B54/B7,"") -> 8703.5 | C55: =IFERROR(C54/B7,"") -> 8144.7665 | D55: =IFERROR(D54/B7,"") -> 9502.4665
A56: Expenses as % of EGI | B56: =IFERROR(B54/B42,"") -> 0.4409877 | C56: =IFERROR(C54/C42,"") -> 0.4168396 | D56: =IF(C38>0,IFERROR(D54/C42,""),"") -> 0.48632509
A57: OM expense test | B57: =IF(ISNUMBER(B54),IF(D54>B54*(1+Assumptions!$B$24),"OM EXPENSES LIGHT","OM expenses reasonable"),"OM expenses not published") -> OM EXPENSES LIGHT
A59: NOI & RETURNS
B60: OM as presented | C60: LAAA underwritten | F60: Basis / note
A61: Net operating income | B61: =B42-B54 -> 220657.56 | C61: =IF(C38>0,C42-D54,"") -> 200737.27 | F61: OM states NOI 220,658 / cap 5.32
A62: Cap rate on asking price | B62: =IFERROR(B61/B22,"") -> 0.053170496 | C62: =IF(C61="","",IFERROR(C61/B22,"")) -> 0.048370427 | F62: OM column recomputed from OM figures; compare to published cap above
A63: GRM (price / scheduled rent) | B63: =IFERROR(B22/B38,"") -> 10.382216 | C63: =IF(C38>0,IFERROR(B22/C38,""),"") -> 10.380709
A64: NOI per unit | B64: =IFERROR(B61/B7,"") -> 11032.878 | C64: =IF(C61="","",IFERROR(C61/B7,"")) -> 10036.863
A66: FINANCING (illustrative, on LAAA NOI)
A67: LTV loan | B67: =IFERROR(B22*Assumptions!$B$20,"") -> 2490000
A68: DCR-sized loan | B68: =IF(C61="","",IFERROR(PV(Assumptions!$B$22/12,Assumptions!$B$23*12,-C61/Assumptions!$B$21/12),"")) -> 2173479.1
A69: Loan amount (lesser of) | B69: =IFERROR(MIN(B67,B68),"") -> 2173479.1
A70: Down payment | B70: =IFERROR(B22-B69,"") -> 1976520.9
A71: Annual debt service | B71: =IFERROR(-PMT(Assumptions!$B$22/12,Assumptions!$B$23*12,B69)*12,"") -> 160589.82
A72: DCR | B72: =IFERROR(C61/B71,"") -> 1.25
A73: Cash flow after debt service | B73: =IFERROR(C61-B71,"") -> 40147.454
A74: Cash-on-cash return | B74: =IFERROR(B73/B70,"") -> 0.020312183
A76: Legend: yellow = published input, orange = estimated (nothing published), grey = LAAA underwritten (MAX of OM line and benchmark; taxes always reassessed).
