Workbook

Sheet Assumptions
A1: LAAA UNDERWRITING BENCHMARKS (edit here; every deal tab reads these)
A3: Vacancy & credit loss (% of GSI) | B3: 0.03 | C3: Standard LA practice; vacant units carried at asking rent inside scheduled GSR
A4: Management fee (% of EGI) | B4: 0.05 | C4: Deal-by-deal agent choice; 5% default, MAX(OM, benchmark) used
A5: Insurance: per unit ($) | B5: 200 | C5: LAAA benchmark = (units x $200) + (gross SF x $1.00)
A6: Insurance: per gross SF ($) | B6: 1
A7: Repairs & maintenance per unit, pre-1990 ($/yr) | B7: 1200
A8: Repairs & maintenance per unit, 1990+ ($/yr) | B8: 800
A9: Utilities per unit, LA City ($/yr) | B9: 1500 | C9: Owner-paid water/sewer/trash/common electric+gas (LA Sanitation bundles trash)
A10: Utilities per unit, Santa Monica ($/yr) | B10: 1800 | C10: Separate trash hauler, higher water rates
A11: Utilities per unit, Beverly Hills / WeHo / Culver ($/yr) | B11: 1600
A12: Contract services per unit ($/yr) | B12: 400 | C12: Landscaping, pest, common-area cleaning
A13: Admin / legal / licenses / rent registration per unit ($/yr) | B13: 250 | C13: Includes RSO/rent-board fees, business license, bookkeeping
A14: Replacement reserves per unit ($/yr) | B14: 300
A15: Property tax rate: Los Angeles City | B15: 0.0125 | C15: Ad valorem + direct assessments, reassessed at purchase price
A16: Property tax rate: Santa Monica | B16: 0.0115
A17: Property tax rate: Beverly Hills | B17: 0.0115
A18: Property tax rate: West Hollywood | B18: 0.012
A19: Property tax rate: Culver City | B19: 0.012
A20: Financing: max LTV | B20: 0.6
A21: Financing: min DCR on LAAA NOI | B21: 1.25 | C21: Loan = lesser of LTV loan and DCR-sized loan
A22: Financing: interest rate | B22: 0.0625
A23: Financing: amortization (years) | B23: 30
A24: OM "light" threshold: LAAA total exceeds OM total by more than | B24: 0.05 | C24: Flags OM EXPENSES LIGHT on the deal tab and Master List
A26: Rent-allocation weights when only GRM is published (relative to 1 Bd)
A27: Studio | B27: 0.7
A28: 1 Bd | B28: 1
A29: 2 Bd | B29: 1.35
A30: 3 Bd | B30: 1.75
A32: Estimated in-place rents when NOTHING is published (orange cells on deal tabs)
A33: Coastal (SM / Venice / WeHo / BH): Studio | B33: 1900
A34: Coastal: 1 Bd | B34: 2400
A35: Coastal: 2 Bd | B35: 3200
A36: Coastal: 3 Bd | B36: 4200
A37: West LA / Palms / Culver: Studio | B37: 1750
A38: West LA / Palms / Culver: 1 Bd | B38: 2200
A39: West LA / Palms / Culver: 2 Bd | B39: 2900
A40: West LA / Palms / Culver: 3 Bd | B40: 3800

Sheet 22 222-228 Idaho Ave
A1: 222-228 Idaho Ave
A2: Santa Monica, CA 90403 | Santa Monica
A3: LoopNet listing | B3: Data pulled 9/17/2026 from LoopNet public listing + rent roll and expenses read from the listing broker's OM (Lee & Associates, Berzack, rent roll 9/1/2026)
A4: NOTE: Two parcels 222 & 228 Idaho | OM: Unit-by-unit rents sum to exactly $50,436/mo; OM annual $605,232 = 12 x $50,436 (matches).; Unit 228-3 (1+1) is VACANT; its $2,800 is the OM's asking rent, included in current GSR per OM.; Three units are owner occupied and 'can be delivered vacant' (228-1 $2,750, 228-6 $3,595, 228-10 $2,800); the O | OM: Unit-by-unit rents sum to exactly $50,436/mo; OM annual $605,232 = 12 x $50,436 (matches).; Unit 228-3 (1+1) is VACANT; its $2,800 is the OM's asking rent, included in current GSR per OM.; Three units are owner occupied and 'can be delivered vacant' (228-1 $2,750, 228-6 $3,595, 228-10 $2,800); the O
A6: PROPERTY
A7: Units | B7: 20
A8: Gross building SF | B8: 15006
A9: Lot SF | B9: 14810
A10: Lot acres | B10: 0.34
A11: Year built | B11: 1954
A12: Stories | B12: 2
A13: Zoning | B13: SMR4YY
A14: Occupancy per listing
A15: APN | B15: 4292-023-001
A16: Assessed value (current) | B16: 9991928
A17: Listing broker(s) | B17: Warren Berzack
A18: Date on market | B18: 8/26/2026
A19: Listing last updated | B19: 9/14/2026
A21: PRICING
A22: Asking price | B22: 7795000
A23: Price per unit | B23: =IFERROR(B22/B7,"") -> 389750
A24: Price per gross SF | B24: =IFERROR(B22/B8,"") -> 519.45888
A25: OM / listing cap rate (as published) | B25: 0.0507
A26: OM / listing GRM (as published) | B26: 12.34
A28: UNIT MIX & SCHEDULED RENT
A29: Unit type | B29: # Units | C29: Avg rent / mo | D29: Monthly total | E29: Annual | F29: Rent source
A30: Studio / 1 Ba [OM market/asking rent 2395; OM avg shown 2,298] | B30: 2 | C30: 2298 | D30: =B30*C30 -> 4596 | E30: =D30*12 -> 55152 | F30: OM rent roll, current in-place rents (OM rent roll 9/1/2026)
A31: 1 Bd / 1 Ba [OM market/asking rent 2775; OM avg shown 2,465; includes vac] | B31: 16 | C31: 2465 | D31: =B31*C31 -> 39440 | E31: =D31*12 -> 473280 | F31: OM rent roll, current in-place rents (OM rent roll 9/1/2026)
A32: 2 Bd / 2 Ba [OM market/asking rent 3595; OM avg shown 3,204; 228-6 owner-] | B32: 2 | C32: 3204 | D32: =B32*C32 -> 6408 | E32: =D32*12 -> 76896 | F32: OM rent roll, current in-place rents (OM rent roll 9/1/2026)
A33: Total / weighted avg | B33: =SUM(B30:B32) -> 20 | C33: =IFERROR(D33/B33,"") -> 2522.2 | D33: =SUM(D30:D32) -> 50444 | E33: =SUM(E30:E32) -> 605328
A35: INCOME
B36: OM as presented | C36: LAAA underwritten | F36: Basis / note
A37: Scheduled gross rent | B37: 605232 | C37: =E33 -> 605328 | F37: OM column: OM stated current scheduled rent (OM rent roll 9/1/2026); LAAA column: OM rent roll by unit type
A38: Other income (laundry, parking, RUBS) | B38: 26400 | C38: 26400
A39: Gross scheduled income | B39: =B37+B38 -> 631632 | C39: =C37+C38 -> 631728
A40: Vacancy & credit loss | B40: =-B37*0.03 -> -18156.96 | C40: =-C37*Assumptions!$B$3 -> -18159.84 | F40: OM 3.0%; LAAA per Assumptions
A41: Effective gross income | B41: =B39+B40 -> 613475.04 | C41: =C39+C40 -> 613568.16
A43: OPERATING EXPENSES
A44: Expense line | B44: OM as presented | C44: LAAA benchmark | D44: LAAA underwritten | E44: Delta vs OM | F44: Basis / note
A45: Property taxes (reassessed at price) | B45: 97438 | C45: =B22*Assumptions!$B$16 -> 89642.5 | D45: =C45 -> 89642.5 | E45: =IF(ISNUMBER(B45),D45-B45,"") -> -7795.5 | F45: Santa Monica rate x asking price; always reassessed, never MAX
A46: Insurance | B46: 18498 | C46: =B7*Assumptions!$B$5+B8*Assumptions!$B$6 -> 19006 | D46: =IF(ISNUMBER(B46),MAX(B46,C46),C46) -> 19006 | E46: =IF(ISNUMBER(B46),D46-B46,"") -> 508 | F46: LAAA benchmark (units x $200) + (SF x $1.00)
A47: Management | B47: 25265 | C47: =C41*Assumptions!$B$4 -> 30678.408 | D47: =IF(ISNUMBER(B47),MAX(B47,C47),C47) -> 30678.408 | E47: =IF(ISNUMBER(B47),D47-B47,"") -> 5413.408 | F47: % of LAAA EGI
A48: Repairs & maintenance | B48: 31280 | C48: =B7*Assumptions!$B$7 -> 24000 | D48: =IF(ISNUMBER(B48),MAX(B48,C48),C48) -> 31280 | E48: =IF(ISNUMBER(B48),D48-B48,"") -> 0 | F48: per unit, by vintage
A49: Utilities (water/sewer/trash/common electric & gas) | B49: 20882 | C49: =B7*Assumptions!$B$10 -> 36000 | D49: =IF(ISNUMBER(B49),MAX(B49,C49),C49) -> 36000 | E49: =IF(ISNUMBER(B49),D49-B49,"") -> 15118 | F49: per unit, by city; OM utilities + water/sewer + gas/electric + trash combined
A50: Contract services (landscape, pest, cleaning) | B50: 3180 | C50: =B7*Assumptions!$B$12 -> 8000 | D50: =IF(ISNUMBER(B50),MAX(B50,C50),C50) -> 8000 | E50: =IF(ISNUMBER(B50),D50-B50,"") -> 4820 | F50: per unit
A51: Admin / legal / licenses / rent registration / other OM items | B51: 21200 | C51: =B7*Assumptions!$B$13 -> 5000 | D51: =IF(ISNUMBER(B51),MAX(B51,C51),C51) -> 21200 | E51: =IF(ISNUMBER(B51),D51-B51,"") -> 0 | F51: OM other items: On-Site Management 14,400; S.M. Unit Registration 4,800; Miscellaneous ($100/unit) 2,000
A52: Replacement reserves | C52: =B7*Assumptions!$B$14 -> 6000 | D52: =IF(ISNUMBER(B52),MAX(B52,C52),C52) -> 6000 | E52: =IF(ISNUMBER(B52),D52-B52,"") | F52: per unit
A53: Total operating expenses | B53: =SUM(B45:B52) -> 217743 | C53: =SUM(C45:C52) -> 218326.91 | D53: =SUM(D45:D52) -> 241806.91 | E53: =IF(ISNUMBER(B53),D53-B53,"") -> 24063.908 | F53: OM line items from OM (OM rent roll 9/1/2026); basis: OM 'Estimated Annual Expenses' (broker estimates, same $217,743 applied to both Current and Market columns). Taxes est. 1.25% of price; R&M $2/SF on 15,640 SF; off-site management 4% of GOI ($631,632); utilities is a single combined line. Vacancy reserve 3% of GOI ($18,949) is shown as a deduction to EGI, not an expense line. Line items sum to $217,743 exactly.; OM total 217,743
A54: Expenses per unit | B54: =IFERROR(B53/B7,"") -> 10887.15 | C54: =IFERROR(C53/B7,"") -> 10916.345 | D54: =IFERROR(D53/B7,"") -> 12090.345
A55: Expenses as % of EGI | B55: =IFERROR(B53/B41,"") -> 0.35493376 | C55: =IFERROR(C53/C41,"") -> 0.35583155 | D55: =IF(C37>0,IFERROR(D53/C41,""),"") -> 0.3940995
A56: OM expense test | B56: =IF(ISNUMBER(B53),IF(D53>B53*(1+Assumptions!$B$24),"OM EXPENSES LIGHT","OM expenses reasonable"),"OM expenses not published") -> OM EXPENSES LIGHT
A58: NOI & RETURNS
B59: OM as presented | C59: LAAA underwritten | F59: Basis / note
A60: Net operating income | B60: =B41-B53 -> 395732.04 | C60: =IF(C37>0,C41-D53,"") -> 371761.25 | F60: OM states NOI 394,940 / cap 5.07
A61: Cap rate on asking price | B61: =IFERROR(B60/B22,"") -> 0.05076742 | C61: =IF(C60="","",IFERROR(C60/B22,"")) -> 0.047692271 | F61: OM column recomputed from OM figures; compare to published cap above
A62: GRM (price / scheduled rent) | B62: =IFERROR(B22/B37,"") -> 12.879359 | C62: =IF(C37>0,IFERROR(B22/C37,""),"") -> 12.877316
A63: NOI per unit | B63: =IFERROR(B60/B7,"") -> 19786.602 | C63: =IF(C60="","",IFERROR(C60/B7,"")) -> 18588.063
A65: FINANCING (illustrative, on LAAA NOI)
A66: LTV loan | B66: =IFERROR(B22*Assumptions!$B$20,"") -> 4677000
A67: DCR-sized loan | B67: =IF(C60="","",IFERROR(PV(Assumptions!$B$22/12,Assumptions!$B$23*12,-C60/Assumptions!$B$21/12),"")) -> 4025238.1
A68: Loan amount (lesser of) | B68: =IFERROR(MIN(B66,B67),"") -> 4025238.1
A69: Down payment | B69: =IFERROR(B22-B68,"") -> 3769761.9
A70: Annual debt service | B70: =IFERROR(-PMT(Assumptions!$B$22/12,Assumptions!$B$23*12,B68)*12,"") -> 297409
A71: DCR | B71: =IFERROR(C60/B70,"") -> 1.25
A72: Cash flow after debt service | B72: =IFERROR(C60-B70,"") -> 74352.25
A73: Cash-on-cash return | B73: =IFERROR(B72/B69,"") -> 0.019723328
A75: Legend: yellow = published input, orange = estimated (nothing published), grey = LAAA underwritten (MAX of OM line and benchmark; taxes always reassessed).
