Workbook

Sheet Assumptions
A1: LAAA UNDERWRITING BENCHMARKS (edit here; every deal tab reads these)
A3: Vacancy & credit loss (% of GSI) | B3: 0.03 | C3: Standard LA practice; vacant units carried at asking rent inside scheduled GSR
A4: Management fee (% of EGI) | B4: 0.05 | C4: Deal-by-deal agent choice; 5% default, MAX(OM, benchmark) used
A5: Insurance: per unit ($) | B5: 200 | C5: LAAA benchmark = (units x $200) + (gross SF x $1.00)
A6: Insurance: per gross SF ($) | B6: 1
A7: Repairs & maintenance per unit, pre-1990 ($/yr) | B7: 1200
A8: Repairs & maintenance per unit, 1990+ ($/yr) | B8: 800
A9: Utilities per unit, LA City ($/yr) | B9: 1500 | C9: Owner-paid water/sewer/trash/common electric+gas (LA Sanitation bundles trash)
A10: Utilities per unit, Santa Monica ($/yr) | B10: 1800 | C10: Separate trash hauler, higher water rates
A11: Utilities per unit, Beverly Hills / WeHo / Culver ($/yr) | B11: 1600
A12: Contract services per unit ($/yr) | B12: 400 | C12: Landscaping, pest, common-area cleaning
A13: Admin / legal / licenses / rent registration per unit ($/yr) | B13: 250 | C13: Includes RSO/rent-board fees, business license, bookkeeping
A14: Replacement reserves per unit ($/yr) | B14: 300
A15: Property tax rate: Los Angeles City | B15: 0.0125 | C15: Ad valorem + direct assessments, reassessed at purchase price
A16: Property tax rate: Santa Monica | B16: 0.0115
A17: Property tax rate: Beverly Hills | B17: 0.0115
A18: Property tax rate: West Hollywood | B18: 0.012
A19: Property tax rate: Culver City | B19: 0.012
A20: Financing: max LTV | B20: 0.6
A21: Financing: min DCR on LAAA NOI | B21: 1.25 | C21: Loan = lesser of LTV loan and DCR-sized loan
A22: Financing: interest rate | B22: 0.0625
A23: Financing: amortization (years) | B23: 30
A24: OM "light" threshold: LAAA total exceeds OM total by more than | B24: 0.05 | C24: Flags OM EXPENSES LIGHT on the deal tab and Master List
A26: Rent-allocation weights when only GRM is published (relative to 1 Bd)
A27: Studio | B27: 0.7
A28: 1 Bd | B28: 1
A29: 2 Bd | B29: 1.35
A30: 3 Bd | B30: 1.75
A32: Estimated in-place rents when NOTHING is published (orange cells on deal tabs)
A33: Coastal (SM / Venice / WeHo / BH): Studio | B33: 1900
A34: Coastal: 1 Bd | B34: 2400
A35: Coastal: 2 Bd | B35: 3200
A36: Coastal: 3 Bd | B36: 4200
A37: West LA / Palms / Culver: Studio | B37: 1750
A38: West LA / Palms / Culver: 1 Bd | B38: 2200
A39: West LA / Palms / Culver: 2 Bd | B39: 2900
A40: West LA / Palms / Culver: 3 Bd | B40: 3800

Sheet 24 8468 Fountain Ave
A1: 8468 Fountain Ave
A2: West Hollywood, CA 90069 | West Hollywood
A3: LoopNet listing | B3: Data pulled 9/17/2026 from LoopNet public listing
A6: PROPERTY
A7: Units | B7: 13
A8: Gross building SF | B8: 13131
A9: Lot SF | B9: 11761
A10: Lot acres | B10: 0.27
A11: Year built | B11: 1939
A12: Stories | B12: 2
A13: Zoning | B13: R4, West Hollywood - Restricted Density Multiple Dwelling
A14: Occupancy per listing | B14: 97%
A15: APN | B15: 5555-004-013
A16: Assessed value (current) | B16: 2254000
A17: Listing broker(s) | B17: Michael Kamara
A18: Date on market | B18: 7/16/2026
A19: Listing last updated | B19: 9/14/2026
A21: PRICING
A22: Asking price | B22: 5995000
A23: Price per unit | B23: =IFERROR(B22/B7,"") -> 461153.85
A24: Price per gross SF | B24: =IFERROR(B22/B8,"") -> 456.55319
A25: OM / listing cap rate (as published) | B25: 0.0488
A26: OM / listing GRM (as published) | B26: 15.13
A28: UNIT MIX & SCHEDULED RENT
A29: Unit type | B29: # Units | C29: Avg rent / mo | D29: Monthly total | E29: Annual | F29: Rent source
A30: Studio | B30: 1 | C30: 1681 | D30: =B30*C30 -> 1681 | E30: =D30*12 -> 20172 | F30: Allocated from published GRM (price / GRM) using LAAA bed weights
A31: 1 Bd / 1 Ba | B31: 9 | C31: 2401 | D31: =B31*C31 -> 21609 | E31: =D31*12 -> 259308 | F31: Allocated from published GRM (price / GRM) using LAAA bed weights
A32: 2 Bd / 2 Ba | B32: 2 | C32: 3242 | D32: =B32*C32 -> 6484 | E32: =D32*12 -> 77808 | F32: Allocated from published GRM (price / GRM) using LAAA bed weights
A33: 2 Bd / 2.5 Ba | B33: 1 | C33: 3242 | D33: =B33*C33 -> 3242 | E33: =D33*12 -> 38904 | F33: Allocated from published GRM (price / GRM) using LAAA bed weights
A34: Total / weighted avg | B34: =SUM(B30:B33) -> 13 | C34: =IFERROR(D34/B34,"") -> 2539.6923 | D34: =SUM(D30:D33) -> 33016 | E34: =SUM(E30:E33) -> 396192
A36: INCOME
B37: OM as presented | C37: LAAA underwritten | F37: Basis / note
A38: Scheduled gross rent | B38: 396232.65 | C38: =E34 -> 396192 | F38: OM column: price / published GRM
A39: Other income (laundry, parking, RUBS) | B39: 0 | C39: 0
A40: Gross scheduled income | B40: =B38+B39 -> 396232.65 | C40: =C38+C39 -> 396192
A41: Vacancy & credit loss | B41: =-B38*0.03 -> -11886.98 | C41: =-C38*Assumptions!$B$3 -> -11885.76 | F41: OM 3.0% (OM figure if extracted, else 3% assumed); LAAA per Assumptions
A42: Effective gross income | B42: =B40+B41 -> 384345.67 | C42: =C40+C41 -> 384306.24
A44: OPERATING EXPENSES
A45: Expense line | B45: OM as presented | C45: LAAA benchmark | D45: LAAA underwritten | E45: Delta vs OM | F45: Basis / note
A46: Property taxes (reassessed at price) | C46: =B22*Assumptions!$B$18 -> 71940 | D46: =C46 -> 71940 | E46: =IF(ISNUMBER(B46),D46-B46,"") | F46: West Hollywood rate x asking price; always reassessed, never MAX
A47: Insurance | C47: =B7*Assumptions!$B$5+B8*Assumptions!$B$6 -> 15731 | D47: =IF(ISNUMBER(B47),MAX(B47,C47),C47) -> 15731 | E47: =IF(ISNUMBER(B47),D47-B47,"") | F47: LAAA benchmark (units x $200) + (SF x $1.00)
A48: Management | C48: =C42*Assumptions!$B$4 -> 19215.312 | D48: =IF(ISNUMBER(B48),MAX(B48,C48),C48) -> 19215.312 | E48: =IF(ISNUMBER(B48),D48-B48,"") | F48: % of LAAA EGI
A49: Repairs & maintenance | C49: =B7*Assumptions!$B$7 -> 15600 | D49: =IF(ISNUMBER(B49),MAX(B49,C49),C49) -> 15600 | E49: =IF(ISNUMBER(B49),D49-B49,"") | F49: per unit, by vintage
A50: Utilities (water/sewer/trash/common electric & gas) | C50: =B7*Assumptions!$B$11 -> 20800 | D50: =IF(ISNUMBER(B50),MAX(B50,C50),C50) -> 20800 | E50: =IF(ISNUMBER(B50),D50-B50,"") | F50: per unit, by city
A51: Contract services (landscape, pest, cleaning) | C51: =B7*Assumptions!$B$12 -> 5200 | D51: =IF(ISNUMBER(B51),MAX(B51,C51),C51) -> 5200 | E51: =IF(ISNUMBER(B51),D51-B51,"") | F51: per unit
A52: Admin / legal / licenses / rent registration | C52: =B7*Assumptions!$B$13 -> 3250 | D52: =IF(ISNUMBER(B52),MAX(B52,C52),C52) -> 3250 | E52: =IF(ISNUMBER(B52),D52-B52,"") | F52: per unit; OM "other" items land here
A53: Replacement reserves | C53: =B7*Assumptions!$B$14 -> 3900 | D53: =IF(ISNUMBER(B53),MAX(B53,C53),C53) -> 3900 | E53: =IF(ISNUMBER(B53),D53-B53,"") | F53: per unit
A54: Total operating expenses | B54: =B42-B22*B25 -> 91789.671 | C54: =SUM(C46:C53) -> 155636.31 | D54: =SUM(D46:D53) -> 155636.31 | E54: =IF(ISNUMBER(B54),D54-B54,"") -> 63846.641 | F54: OM line items not published. OM total IMPLIED = OM EGI - (price x published cap)
A55: Expenses per unit | B55: =IFERROR(B54/B7,"") -> 7060.7439 | C55: =IFERROR(C54/B7,"") -> 11972.024 | D55: =IFERROR(D54/B7,"") -> 11972.024
A56: Expenses as % of EGI | B56: =IFERROR(B54/B42,"") -> 0.23882062 | C56: =IFERROR(C54/C42,"") -> 0.40497992 | D56: =IF(C38>0,IFERROR(D54/C42,""),"") -> 0.40497992
A57: OM expense test | B57: =IF(ISNUMBER(B54),IF(D54>B54*(1+Assumptions!$B$24),"OM EXPENSES LIGHT","OM expenses reasonable"),"OM expenses not published") -> OM EXPENSES LIGHT
A59: NOI & RETURNS
B60: OM as presented | C60: LAAA underwritten | F60: Basis / note
A61: Net operating income | B61: =B42-B54 -> 292556 | C61: =IF(C38>0,C42-D54,"") -> 228669.93
A62: Cap rate on asking price | B62: =IFERROR(B61/B22,"") -> 0.0488 | C62: =IF(C61="","",IFERROR(C61/B22,"")) -> 0.038143441 | F62: OM column recomputed from OM figures; compare to published cap above
A63: GRM (price / scheduled rent) | B63: =IFERROR(B22/B38,"") -> 15.13 | C63: =IF(C38>0,IFERROR(B22/C38,""),"") -> 15.131552
A64: NOI per unit | B64: =IFERROR(B61/B7,"") -> 22504.308 | C64: =IF(C61="","",IFERROR(C61/B7,"")) -> 17589.994
A66: FINANCING (illustrative, on LAAA NOI)
A67: LTV loan | B67: =IFERROR(B22*Assumptions!$B$20,"") -> 3597000
A68: DCR-sized loan | B68: =IF(C61="","",IFERROR(PV(Assumptions!$B$22/12,Assumptions!$B$23*12,-C61/Assumptions!$B$21/12),"")) -> 2475919.4
A69: Loan amount (lesser of) | B69: =IFERROR(MIN(B67,B68),"") -> 2475919.4
A70: Down payment | B70: =IFERROR(B22-B69,"") -> 3519080.6
A71: Annual debt service | B71: =IFERROR(-PMT(Assumptions!$B$22/12,Assumptions!$B$23*12,B69)*12,"") -> 182935.94
A72: DCR | B72: =IFERROR(C61/B71,"") -> 1.25
A73: Cash flow after debt service | B73: =IFERROR(C61-B71,"") -> 45733.986
A74: Cash-on-cash return | B74: =IFERROR(B73/B70,"") -> 0.012996004
A76: Legend: yellow = published input, orange = estimated (nothing published), grey = LAAA underwritten (MAX of OM line and benchmark; taxes always reassessed).
