Workbook

Sheet Assumptions
A1: LAAA UNDERWRITING BENCHMARKS (edit here; every deal tab reads these)
A3: Vacancy & credit loss (% of GSI) | B3: 0.03 | C3: Standard LA practice; vacant units carried at asking rent inside scheduled GSR
A4: Management fee (% of EGI) | B4: 0.05 | C4: Deal-by-deal agent choice; 5% default, MAX(OM, benchmark) used
A5: Insurance: per unit ($) | B5: 200 | C5: LAAA benchmark = (units x $200) + (gross SF x $1.00)
A6: Insurance: per gross SF ($) | B6: 1
A7: Repairs & maintenance per unit, pre-1990 ($/yr) | B7: 1200
A8: Repairs & maintenance per unit, 1990+ ($/yr) | B8: 800
A9: Utilities per unit, LA City ($/yr) | B9: 1500 | C9: Owner-paid water/sewer/trash/common electric+gas (LA Sanitation bundles trash)
A10: Utilities per unit, Santa Monica ($/yr) | B10: 1800 | C10: Separate trash hauler, higher water rates
A11: Utilities per unit, Beverly Hills / WeHo / Culver ($/yr) | B11: 1600
A12: Contract services per unit ($/yr) | B12: 400 | C12: Landscaping, pest, common-area cleaning
A13: Admin / legal / licenses / rent registration per unit ($/yr) | B13: 250 | C13: Includes RSO/rent-board fees, business license, bookkeeping
A14: Replacement reserves per unit ($/yr) | B14: 300
A15: Property tax rate: Los Angeles City | B15: 0.0125 | C15: Ad valorem + direct assessments, reassessed at purchase price
A16: Property tax rate: Santa Monica | B16: 0.0115
A17: Property tax rate: Beverly Hills | B17: 0.0115
A18: Property tax rate: West Hollywood | B18: 0.012
A19: Property tax rate: Culver City | B19: 0.012
A20: Financing: max LTV | B20: 0.6
A21: Financing: min DCR on LAAA NOI | B21: 1.25 | C21: Loan = lesser of LTV loan and DCR-sized loan
A22: Financing: interest rate | B22: 0.0625
A23: Financing: amortization (years) | B23: 30
A24: OM "light" threshold: LAAA total exceeds OM total by more than | B24: 0.05 | C24: Flags OM EXPENSES LIGHT on the deal tab and Master List
A26: Rent-allocation weights when only GRM is published (relative to 1 Bd)
A27: Studio | B27: 0.7
A28: 1 Bd | B28: 1
A29: 2 Bd | B29: 1.35
A30: 3 Bd | B30: 1.75
A32: Estimated in-place rents when NOTHING is published (orange cells on deal tabs)
A33: Coastal (SM / Venice / WeHo / BH): Studio | B33: 1900
A34: Coastal: 1 Bd | B34: 2400
A35: Coastal: 2 Bd | B35: 3200
A36: Coastal: 3 Bd | B36: 4200
A37: West LA / Palms / Culver: Studio | B37: 1750
A38: West LA / Palms / Culver: 1 Bd | B38: 2200
A39: West LA / Palms / Culver: 2 Bd | B39: 2900
A40: West LA / Palms / Culver: 3 Bd | B40: 3800

Sheet 29 1307 15th St
A1: 1307 15th St
A2: Santa Monica, CA 90404 | Santa Monica
A3: LoopNet listing | B3: Data pulled 9/17/2026 from LoopNet public listing
A6: PROPERTY
A7: Units | B7: 11
A8: Gross building SF | B8: 8398
A9: Lot SF | B9: 7405
A10: Lot acres | B10: 0.17
A11: Year built | B11: 1958
A12: Stories | B12: 2
A13: Zoning | B13: CP, Santa Monica - CP (Commercial Pedestrian) zoning supports pedestrian-oriented retail, restaurant, office, and service uses within a walkable commercial district.
A14: Occupancy per listing | B14: 91%
A15: APN | B15: 4282-017-034
A16: Assessed value (current) | B16: 2574851
A17: Listing broker(s) | B17: William Dawson
A18: Date on market | B18: 6/3/2025
A19: Listing last updated | B19: 9/11/2026
A21: PRICING
A22: Asking price | B22: 3850000
A23: Price per unit | B23: =IFERROR(B22/B7,"") -> 350000
A24: Price per gross SF | B24: =IFERROR(B22/B8,"") -> 458.44249
A25: OM / listing cap rate (as published) | B25: 0.0434
A26: OM / listing GRM (as published) | B26: 14.29
A28: UNIT MIX & SCHEDULED RENT
A29: Unit type | B29: # Units | C29: Avg rent / mo | D29: Monthly total | E29: Annual | F29: Rent source
A30: Studio | B30: 2 | C30: 1373 | D30: =B30*C30 -> 2746 | E30: =D30*12 -> 32952 | F30: Allocated from published GRM (price / GRM) using LAAA bed weights
A31: 1 Bd / 1 Ba | B31: 6 | C31: 1961 | D31: =B31*C31 -> 11766 | E31: =D31*12 -> 141192 | F31: Allocated from published GRM (price / GRM) using LAAA bed weights
A32: 2 Bd / 1 Ba | B32: 3 | C32: 2647 | D32: =B32*C32 -> 7941 | E32: =D32*12 -> 95292 | F32: Allocated from published GRM (price / GRM) using LAAA bed weights
A33: Total / weighted avg | B33: =SUM(B30:B32) -> 11 | C33: =IFERROR(D33/B33,"") -> 2041.1818 | D33: =SUM(D30:D32) -> 22453 | E33: =SUM(E30:E32) -> 269436
A35: INCOME
B36: OM as presented | C36: LAAA underwritten | F36: Basis / note
A37: Scheduled gross rent | B37: 269419.17 | C37: =E33 -> 269436 | F37: OM column: price / published GRM
A38: Other income (laundry, parking, RUBS) | B38: 0 | C38: 0
A39: Gross scheduled income | B39: =B37+B38 -> 269419.17 | C39: =C37+C38 -> 269436
A40: Vacancy & credit loss | B40: =-B37*0.03 -> -8082.5752 | C40: =-C37*Assumptions!$B$3 -> -8083.08 | F40: OM 3.0% (OM figure if extracted, else 3% assumed); LAAA per Assumptions
A41: Effective gross income | B41: =B39+B40 -> 261336.6 | C41: =C39+C40 -> 261352.92
A43: OPERATING EXPENSES
A44: Expense line | B44: OM as presented | C44: LAAA benchmark | D44: LAAA underwritten | E44: Delta vs OM | F44: Basis / note
A45: Property taxes (reassessed at price) | C45: =B22*Assumptions!$B$16 -> 44275 | D45: =C45 -> 44275 | E45: =IF(ISNUMBER(B45),D45-B45,"") | F45: Santa Monica rate x asking price; always reassessed, never MAX
A46: Insurance | C46: =B7*Assumptions!$B$5+B8*Assumptions!$B$6 -> 10598 | D46: =IF(ISNUMBER(B46),MAX(B46,C46),C46) -> 10598 | E46: =IF(ISNUMBER(B46),D46-B46,"") | F46: LAAA benchmark (units x $200) + (SF x $1.00)
A47: Management | C47: =C41*Assumptions!$B$4 -> 13067.646 | D47: =IF(ISNUMBER(B47),MAX(B47,C47),C47) -> 13067.646 | E47: =IF(ISNUMBER(B47),D47-B47,"") | F47: % of LAAA EGI
A48: Repairs & maintenance | C48: =B7*Assumptions!$B$7 -> 13200 | D48: =IF(ISNUMBER(B48),MAX(B48,C48),C48) -> 13200 | E48: =IF(ISNUMBER(B48),D48-B48,"") | F48: per unit, by vintage
A49: Utilities (water/sewer/trash/common electric & gas) | C49: =B7*Assumptions!$B$10 -> 19800 | D49: =IF(ISNUMBER(B49),MAX(B49,C49),C49) -> 19800 | E49: =IF(ISNUMBER(B49),D49-B49,"") | F49: per unit, by city
A50: Contract services (landscape, pest, cleaning) | C50: =B7*Assumptions!$B$12 -> 4400 | D50: =IF(ISNUMBER(B50),MAX(B50,C50),C50) -> 4400 | E50: =IF(ISNUMBER(B50),D50-B50,"") | F50: per unit
A51: Admin / legal / licenses / rent registration | C51: =B7*Assumptions!$B$13 -> 2750 | D51: =IF(ISNUMBER(B51),MAX(B51,C51),C51) -> 2750 | E51: =IF(ISNUMBER(B51),D51-B51,"") | F51: per unit; OM "other" items land here
A52: Replacement reserves | C52: =B7*Assumptions!$B$14 -> 3300 | D52: =IF(ISNUMBER(B52),MAX(B52,C52),C52) -> 3300 | E52: =IF(ISNUMBER(B52),D52-B52,"") | F52: per unit
A53: Total operating expenses | B53: =B41-B22*B25 -> 94246.599 | C53: =SUM(C45:C52) -> 111390.65 | D53: =SUM(D45:D52) -> 111390.65 | E53: =IF(ISNUMBER(B53),D53-B53,"") -> 17144.047 | F53: OM line items not published. OM total IMPLIED = OM EGI - (price x published cap)
A54: Expenses per unit | B54: =IFERROR(B53/B7,"") -> 8567.8726 | C54: =IFERROR(C53/B7,"") -> 10126.422 | D54: =IFERROR(D53/B7,"") -> 10126.422
A55: Expenses as % of EGI | B55: =IFERROR(B53/B41,"") -> 0.36063299 | C55: =IFERROR(C53/C41,"") -> 0.42620777 | D55: =IF(C37>0,IFERROR(D53/C41,""),"") -> 0.42620777
A56: OM expense test | B56: =IF(ISNUMBER(B53),IF(D53>B53*(1+Assumptions!$B$24),"OM EXPENSES LIGHT","OM expenses reasonable"),"OM expenses not published") -> OM EXPENSES LIGHT
A58: NOI & RETURNS
B59: OM as presented | C59: LAAA underwritten | F59: Basis / note
A60: Net operating income | B60: =B41-B53 -> 167090 | C60: =IF(C37>0,C41-D53,"") -> 149962.27
A61: Cap rate on asking price | B61: =IFERROR(B60/B22,"") -> 0.0434 | C61: =IF(C60="","",IFERROR(C60/B22,"")) -> 0.03895124 | F61: OM column recomputed from OM figures; compare to published cap above
A62: GRM (price / scheduled rent) | B62: =IFERROR(B22/B37,"") -> 14.29 | C62: =IF(C37>0,IFERROR(B22/C37,""),"") -> 14.289108
A63: NOI per unit | B63: =IFERROR(B60/B7,"") -> 15190 | C63: =IF(C60="","",IFERROR(C60/B7,"")) -> 13632.934
A65: FINANCING (illustrative, on LAAA NOI)
A66: LTV loan | B66: =IFERROR(B22*Assumptions!$B$20,"") -> 2310000
A67: DCR-sized loan | B67: =IF(C60="","",IFERROR(PV(Assumptions!$B$22/12,Assumptions!$B$23*12,-C60/Assumptions!$B$21/12),"")) -> 1623713.8
A68: Loan amount (lesser of) | B68: =IFERROR(MIN(B66,B67),"") -> 1623713.8
A69: Down payment | B69: =IFERROR(B22-B68,"") -> 2226286.2
A70: Annual debt service | B70: =IFERROR(-PMT(Assumptions!$B$22/12,Assumptions!$B$23*12,B68)*12,"") -> 119969.82
A71: DCR | B71: =IFERROR(C60/B70,"") -> 1.25
A72: Cash flow after debt service | B72: =IFERROR(C60-B70,"") -> 29992.455
A73: Cash-on-cash return | B73: =IFERROR(B72/B69,"") -> 0.013471967
A75: Legend: yellow = published input, orange = estimated (nothing published), grey = LAAA underwritten (MAX of OM line and benchmark; taxes always reassessed).
