Workbook

Sheet Assumptions
A1: LAAA UNDERWRITING BENCHMARKS (edit here; every deal tab reads these)
A3: Vacancy & credit loss (% of GSI) | B3: 0.03 | C3: Standard LA practice; vacant units carried at asking rent inside scheduled GSR
A4: Management fee (% of EGI) | B4: 0.05 | C4: Deal-by-deal agent choice; 5% default, MAX(OM, benchmark) used
A5: Insurance: per unit ($) | B5: 200 | C5: LAAA benchmark = (units x $200) + (gross SF x $1.00)
A6: Insurance: per gross SF ($) | B6: 1
A7: Repairs & maintenance per unit, pre-1990 ($/yr) | B7: 1200
A8: Repairs & maintenance per unit, 1990+ ($/yr) | B8: 800
A9: Utilities per unit, LA City ($/yr) | B9: 1500 | C9: Owner-paid water/sewer/trash/common electric+gas (LA Sanitation bundles trash)
A10: Utilities per unit, Santa Monica ($/yr) | B10: 1800 | C10: Separate trash hauler, higher water rates
A11: Utilities per unit, Beverly Hills / WeHo / Culver ($/yr) | B11: 1600
A12: Contract services per unit ($/yr) | B12: 400 | C12: Landscaping, pest, common-area cleaning
A13: Admin / legal / licenses / rent registration per unit ($/yr) | B13: 250 | C13: Includes RSO/rent-board fees, business license, bookkeeping
A14: Replacement reserves per unit ($/yr) | B14: 300
A15: Property tax rate: Los Angeles City | B15: 0.0125 | C15: Ad valorem + direct assessments, reassessed at purchase price
A16: Property tax rate: Santa Monica | B16: 0.0115
A17: Property tax rate: Beverly Hills | B17: 0.0115
A18: Property tax rate: West Hollywood | B18: 0.012
A19: Property tax rate: Culver City | B19: 0.012
A20: Financing: max LTV | B20: 0.6
A21: Financing: min DCR on LAAA NOI | B21: 1.25 | C21: Loan = lesser of LTV loan and DCR-sized loan
A22: Financing: interest rate | B22: 0.0625
A23: Financing: amortization (years) | B23: 30
A24: OM "light" threshold: LAAA total exceeds OM total by more than | B24: 0.05 | C24: Flags OM EXPENSES LIGHT on the deal tab and Master List
A26: Rent-allocation weights when only GRM is published (relative to 1 Bd)
A27: Studio | B27: 0.7
A28: 1 Bd | B28: 1
A29: 2 Bd | B29: 1.35
A30: 3 Bd | B30: 1.75
A32: Estimated in-place rents when NOTHING is published (orange cells on deal tabs)
A33: Coastal (SM / Venice / WeHo / BH): Studio | B33: 1900
A34: Coastal: 1 Bd | B34: 2400
A35: Coastal: 2 Bd | B35: 3200
A36: Coastal: 3 Bd | B36: 4200
A37: West LA / Palms / Culver: Studio | B37: 1750
A38: West LA / Palms / Culver: 1 Bd | B38: 2200
A39: West LA / Palms / Culver: 2 Bd | B39: 2900
A40: West LA / Palms / Culver: 3 Bd | B40: 3800

Sheet 31 3602 Keystone Ave
A1: 3602 Keystone Ave
A2: Los Angeles, CA 90034 | Palms
A3: LoopNet listing | B3: Data pulled 9/17/2026 from LoopNet public listing
A4: NOTE: 80% occupied
A6: PROPERTY
A7: Units | B7: 10
A8: Gross building SF | B8: 7032
A9: Lot SF | B9: 7405
A10: Lot acres | B10: 0.17
A11: Year built | B11: 1967
A12: Stories | B12: 2
A13: Zoning | B13: LAR3 - Restricted Density Multiple Dwelling
A14: Occupancy per listing | B14: 80%
A15: APN | B15: 4314-009-036
A16: Assessed value (current) | B16: 2610677
A17: Listing broker(s) | B17: Peter James, Will James
A18: Date on market | B18: 8/13/2026
A19: Listing last updated | B19: 9/8/2026
A21: PRICING
A22: Asking price | B22: 2675000
A23: Price per unit | B23: =IFERROR(B22/B7,"") -> 267500
A24: Price per gross SF | B24: =IFERROR(B22/B8,"") -> 380.40387
A25: OM / listing cap rate (as published) | B25: 0.0561
A26: OM / listing GRM (as published) | B26: 11.19
A28: UNIT MIX & SCHEDULED RENT
A29: Unit type | B29: # Units | C29: Avg rent / mo | D29: Monthly total | E29: Annual | F29: Rent source
A30: 1 Bd / 1 Ba | B30: 7 | C30: 2250 | D30: =B30*C30 -> 15750 | E30: =D30*12 -> 189000 | F30: LoopNet published avg rent by unit type
A31: 2 Bd / 1.5 Ba | B31: 2 | C31: 2750 | D31: =B31*C31 -> 5500 | E31: =D31*12 -> 66000 | F31: LoopNet published avg rent by unit type
A32: Studio | B32: 1 | C32: 1650 | D32: =B32*C32 -> 1650 | E32: =D32*12 -> 19800 | F32: LoopNet published avg rent by unit type
A33: Total / weighted avg | B33: =SUM(B30:B32) -> 10 | C33: =IFERROR(D33/B33,"") -> 2290 | D33: =SUM(D30:D32) -> 22900 | E33: =SUM(E30:E32) -> 274800
A35: INCOME
B36: OM as presented | C36: LAAA underwritten | F36: Basis / note
A37: Scheduled gross rent | B37: 239052.73 | C37: =E33 -> 274800 | F37: OM column: price / published GRM
A38: Other income (laundry, parking, RUBS) | B38: 0 | C38: 0
A39: Gross scheduled income | B39: =B37+B38 -> 239052.73 | C39: =C37+C38 -> 274800
A40: Vacancy & credit loss | B40: =-B37*0.03 -> -7171.5818 | C40: =-C37*Assumptions!$B$3 -> -8244 | F40: OM 3.0% (OM figure if extracted, else 3% assumed); LAAA per Assumptions
A41: Effective gross income | B41: =B39+B40 -> 231881.14 | C41: =C39+C40 -> 266556
A43: OPERATING EXPENSES
A44: Expense line | B44: OM as presented | C44: LAAA benchmark | D44: LAAA underwritten | E44: Delta vs OM | F44: Basis / note
A45: Property taxes (reassessed at price) | C45: =B22*Assumptions!$B$15 -> 33437.5 | D45: =C45 -> 33437.5 | E45: =IF(ISNUMBER(B45),D45-B45,"") | F45: Los Angeles rate x asking price; always reassessed, never MAX
A46: Insurance | C46: =B7*Assumptions!$B$5+B8*Assumptions!$B$6 -> 9032 | D46: =IF(ISNUMBER(B46),MAX(B46,C46),C46) -> 9032 | E46: =IF(ISNUMBER(B46),D46-B46,"") | F46: LAAA benchmark (units x $200) + (SF x $1.00)
A47: Management | C47: =C41*Assumptions!$B$4 -> 13327.8 | D47: =IF(ISNUMBER(B47),MAX(B47,C47),C47) -> 13327.8 | E47: =IF(ISNUMBER(B47),D47-B47,"") | F47: % of LAAA EGI
A48: Repairs & maintenance | C48: =B7*Assumptions!$B$7 -> 12000 | D48: =IF(ISNUMBER(B48),MAX(B48,C48),C48) -> 12000 | E48: =IF(ISNUMBER(B48),D48-B48,"") | F48: per unit, by vintage
A49: Utilities (water/sewer/trash/common electric & gas) | C49: =B7*Assumptions!$B$9 -> 15000 | D49: =IF(ISNUMBER(B49),MAX(B49,C49),C49) -> 15000 | E49: =IF(ISNUMBER(B49),D49-B49,"") | F49: per unit, by city
A50: Contract services (landscape, pest, cleaning) | C50: =B7*Assumptions!$B$12 -> 4000 | D50: =IF(ISNUMBER(B50),MAX(B50,C50),C50) -> 4000 | E50: =IF(ISNUMBER(B50),D50-B50,"") | F50: per unit
A51: Admin / legal / licenses / rent registration | C51: =B7*Assumptions!$B$13 -> 2500 | D51: =IF(ISNUMBER(B51),MAX(B51,C51),C51) -> 2500 | E51: =IF(ISNUMBER(B51),D51-B51,"") | F51: per unit; OM "other" items land here
A52: Replacement reserves | C52: =B7*Assumptions!$B$14 -> 3000 | D52: =IF(ISNUMBER(B52),MAX(B52,C52),C52) -> 3000 | E52: =IF(ISNUMBER(B52),D52-B52,"") | F52: per unit
A53: Total operating expenses | B53: =B41-B22*B25 -> 81813.644 | C53: =SUM(C45:C52) -> 92297.3 | D53: =SUM(D45:D52) -> 92297.3 | E53: =IF(ISNUMBER(B53),D53-B53,"") -> 10483.656 | F53: OM line items not published. OM total IMPLIED = OM EGI - (price x published cap)
A54: Expenses per unit | B54: =IFERROR(B53/B7,"") -> 8181.3644 | C54: =IFERROR(C53/B7,"") -> 9229.73 | D54: =IFERROR(D53/B7,"") -> 9229.73
A55: Expenses as % of EGI | B55: =IFERROR(B53/B41,"") -> 0.35282577 | C55: =IFERROR(C53/C41,"") -> 0.34625857 | D55: =IF(C37>0,IFERROR(D53/C41,""),"") -> 0.34625857
A56: OM expense test | B56: =IF(ISNUMBER(B53),IF(D53>B53*(1+Assumptions!$B$24),"OM EXPENSES LIGHT","OM expenses reasonable"),"OM expenses not published") -> OM EXPENSES LIGHT
A58: NOI & RETURNS
B59: OM as presented | C59: LAAA underwritten | F59: Basis / note
A60: Net operating income | B60: =B41-B53 -> 150067.5 | C60: =IF(C37>0,C41-D53,"") -> 174258.7
A61: Cap rate on asking price | B61: =IFERROR(B60/B22,"") -> 0.0561 | C61: =IF(C60="","",IFERROR(C60/B22,"")) -> 0.065143439 | F61: OM column recomputed from OM figures; compare to published cap above
A62: GRM (price / scheduled rent) | B62: =IFERROR(B22/B37,"") -> 11.19 | C62: =IF(C37>0,IFERROR(B22/C37,""),"") -> 9.7343523
A63: NOI per unit | B63: =IFERROR(B60/B7,"") -> 15006.75 | C63: =IF(C60="","",IFERROR(C60/B7,"")) -> 17425.87
A65: FINANCING (illustrative, on LAAA NOI)
A66: LTV loan | B66: =IFERROR(B22*Assumptions!$B$20,"") -> 1605000
A67: DCR-sized loan | B67: =IF(C60="","",IFERROR(PV(Assumptions!$B$22/12,Assumptions!$B$23*12,-C60/Assumptions!$B$21/12),"")) -> 1886782.9
A68: Loan amount (lesser of) | B68: =IFERROR(MIN(B66,B67),"") -> 1605000
A69: Down payment | B69: =IFERROR(B22-B68,"") -> 1070000
A70: Annual debt service | B70: =IFERROR(-PMT(Assumptions!$B$22/12,Assumptions!$B$23*12,B68)*12,"") -> 118587.13
A71: DCR | B71: =IFERROR(C60/B70,"") -> 1.4694571
A72: Cash flow after debt service | B72: =IFERROR(C60-B70,"") -> 55671.567
A73: Cash-on-cash return | B73: =IFERROR(B72/B69,"") -> 0.052029502
A75: Legend: yellow = published input, orange = estimated (nothing published), grey = LAAA underwritten (MAX of OM line and benchmark; taxes always reassessed).
