Workbook

Sheet Assumptions
A1: LAAA UNDERWRITING BENCHMARKS (edit here; every deal tab reads these)
A3: Vacancy & credit loss (% of GSI) | B3: 0.03 | C3: Standard LA practice; vacant units carried at asking rent inside scheduled GSR
A4: Management fee (% of EGI) | B4: 0.05 | C4: Deal-by-deal agent choice; 5% default, MAX(OM, benchmark) used
A5: Insurance: per unit ($) | B5: 200 | C5: LAAA benchmark = (units x $200) + (gross SF x $1.00)
A6: Insurance: per gross SF ($) | B6: 1
A7: Repairs & maintenance per unit, pre-1990 ($/yr) | B7: 1200
A8: Repairs & maintenance per unit, 1990+ ($/yr) | B8: 800
A9: Utilities per unit, LA City ($/yr) | B9: 1500 | C9: Owner-paid water/sewer/trash/common electric+gas (LA Sanitation bundles trash)
A10: Utilities per unit, Santa Monica ($/yr) | B10: 1800 | C10: Separate trash hauler, higher water rates
A11: Utilities per unit, Beverly Hills / WeHo / Culver ($/yr) | B11: 1600
A12: Contract services per unit ($/yr) | B12: 400 | C12: Landscaping, pest, common-area cleaning
A13: Admin / legal / licenses / rent registration per unit ($/yr) | B13: 250 | C13: Includes RSO/rent-board fees, business license, bookkeeping
A14: Replacement reserves per unit ($/yr) | B14: 300
A15: Property tax rate: Los Angeles City | B15: 0.0125 | C15: Ad valorem + direct assessments, reassessed at purchase price
A16: Property tax rate: Santa Monica | B16: 0.0115
A17: Property tax rate: Beverly Hills | B17: 0.0115
A18: Property tax rate: West Hollywood | B18: 0.012
A19: Property tax rate: Culver City | B19: 0.012
A20: Financing: max LTV | B20: 0.6
A21: Financing: min DCR on LAAA NOI | B21: 1.25 | C21: Loan = lesser of LTV loan and DCR-sized loan
A22: Financing: interest rate | B22: 0.0625
A23: Financing: amortization (years) | B23: 30
A24: OM "light" threshold: LAAA total exceeds OM total by more than | B24: 0.05 | C24: Flags OM EXPENSES LIGHT on the deal tab and Master List
A26: Rent-allocation weights when only GRM is published (relative to 1 Bd)
A27: Studio | B27: 0.7
A28: 1 Bd | B28: 1
A29: 2 Bd | B29: 1.35
A30: 3 Bd | B30: 1.75
A32: Estimated in-place rents when NOTHING is published (orange cells on deal tabs)
A33: Coastal (SM / Venice / WeHo / BH): Studio | B33: 1900
A34: Coastal: 1 Bd | B34: 2400
A35: Coastal: 2 Bd | B35: 3200
A36: Coastal: 3 Bd | B36: 4200
A37: West LA / Palms / Culver: Studio | B37: 1750
A38: West LA / Palms / Culver: 1 Bd | B38: 2200
A39: West LA / Palms / Culver: 2 Bd | B39: 2900
A40: West LA / Palms / Culver: 3 Bd | B40: 3800

Sheet 37 Beverly Hills double lot
A1: Beverly Hills double lot (18 units, 2 bldgs)
A2: Beverly Hills, CA 90211 | Beverly Hills
A3: LoopNet listing | B3: Data pulled 9/17/2026 from LoopNet public listing
A4: NOTE: Address not published on LoopNet; 15,751 SF combined lot; 6 of 10 units in one bldg delivered vacant. No financials published
A6: PROPERTY
A7: Units | B7: 18
A8: Gross building SF | B8: 18404
A9: Lot SF | B9: 15751
A10: Lot acres | B10: 0.362
A11: Year built
A12: Stories
A13: Zoning
A14: Occupancy per listing
A15: APN
A16: Assessed value (current)
A17: Listing broker(s) | B17: Adrienne Barr, Nancy Badzey
A18: Date on market | B18: 6/30/2026
A19: Listing last updated | B19: 9/14/2026
A21: PRICING
A22: Asking price | B22: 10000000
A23: Price per unit | B23: =IFERROR(B22/B7,"") -> 555555.56
A24: Price per gross SF | B24: =IFERROR(B22/B8,"") -> 543.36014
A25: OM / listing cap rate (as published)
A26: OM / listing GRM (as published)
A28: UNIT MIX & SCHEDULED RENT
A29: Unit type | B29: # Units | C29: Avg rent / mo | D29: Monthly total | E29: Annual | F29: Rent source
A30: 1 Bd / 1 Ba | B30: 12 | C30: 2400 | D30: =B30*C30 -> 28800 | E30: =D30*12 -> 345600 | F30: ESTIMATED (no rents, GRM or cap published) - verify with OM
A31: 2 Bd / 1 Ba | B31: 6 | C31: 3200 | D31: =B31*C31 -> 19200 | E31: =D31*12 -> 230400 | F31: ESTIMATED (no rents, GRM or cap published) - verify with OM
A32: Total / weighted avg | B32: =SUM(B30:B31) -> 18 | C32: =IFERROR(D32/B32,"") -> 2666.6667 | D32: =SUM(D30:D31) -> 48000 | E32: =SUM(E30:E31) -> 576000
A33: Unit mix not published; 18 units split assumed 12x1BR / 6x2BR
A35: INCOME
B36: OM as presented | C36: LAAA underwritten | F36: Basis / note
A37: Scheduled gross rent | C37: =E32 -> 576000 | F37: OM GSR not published
A38: Other income (laundry, parking, RUBS) | B38: 0 | C38: 0
A39: Gross scheduled income | B39: =B37+B38 -> 0 | C39: =C37+C38 -> 576000
A40: Vacancy & credit loss | B40: =-B37*0.03 -> 0 | C40: =-C37*Assumptions!$B$3 -> -17280 | F40: OM 3.0% (OM figure if extracted, else 3% assumed); LAAA per Assumptions
A41: Effective gross income | B41: =B39+B40 -> 0 | C41: =C39+C40 -> 558720
A43: OPERATING EXPENSES
A44: Expense line | B44: OM as presented | C44: LAAA benchmark | D44: LAAA underwritten | E44: Delta vs OM | F44: Basis / note
A45: Property taxes (reassessed at price) | C45: =B22*Assumptions!$B$17 -> 115000 | D45: =C45 -> 115000 | E45: =IF(ISNUMBER(B45),D45-B45,"") | F45: Beverly Hills rate x asking price; always reassessed, never MAX
A46: Insurance | C46: =B7*Assumptions!$B$5+B8*Assumptions!$B$6 -> 22004 | D46: =IF(ISNUMBER(B46),MAX(B46,C46),C46) -> 22004 | E46: =IF(ISNUMBER(B46),D46-B46,"") | F46: LAAA benchmark (units x $200) + (SF x $1.00)
A47: Management | C47: =C41*Assumptions!$B$4 -> 27936 | D47: =IF(ISNUMBER(B47),MAX(B47,C47),C47) -> 27936 | E47: =IF(ISNUMBER(B47),D47-B47,"") | F47: % of LAAA EGI
A48: Repairs & maintenance | C48: =B7*Assumptions!$B$7 -> 21600 | D48: =IF(ISNUMBER(B48),MAX(B48,C48),C48) -> 21600 | E48: =IF(ISNUMBER(B48),D48-B48,"") | F48: per unit, by vintage
A49: Utilities (water/sewer/trash/common electric & gas) | C49: =B7*Assumptions!$B$11 -> 28800 | D49: =IF(ISNUMBER(B49),MAX(B49,C49),C49) -> 28800 | E49: =IF(ISNUMBER(B49),D49-B49,"") | F49: per unit, by city
A50: Contract services (landscape, pest, cleaning) | C50: =B7*Assumptions!$B$12 -> 7200 | D50: =IF(ISNUMBER(B50),MAX(B50,C50),C50) -> 7200 | E50: =IF(ISNUMBER(B50),D50-B50,"") | F50: per unit
A51: Admin / legal / licenses / rent registration | C51: =B7*Assumptions!$B$13 -> 4500 | D51: =IF(ISNUMBER(B51),MAX(B51,C51),C51) -> 4500 | E51: =IF(ISNUMBER(B51),D51-B51,"") | F51: per unit; OM "other" items land here
A52: Replacement reserves | C52: =B7*Assumptions!$B$14 -> 5400 | D52: =IF(ISNUMBER(B52),MAX(B52,C52),C52) -> 5400 | E52: =IF(ISNUMBER(B52),D52-B52,"") | F52: per unit
A53: Total operating expenses | C53: =SUM(C45:C52) -> 232440 | D53: =SUM(D45:D52) -> 232440 | E53: =IF(ISNUMBER(B53),D53-B53,"") | F53: OM expenses not published
A54: Expenses per unit | B54: =IFERROR(B53/B7,"") -> 0 | C54: =IFERROR(C53/B7,"") -> 12913.333 | D54: =IFERROR(D53/B7,"") -> 12913.333
A55: Expenses as % of EGI | B55: =IFERROR(B53/B41,"") | C55: =IFERROR(C53/C41,"") -> 0.41602234 | D55: =IF(C37>0,IFERROR(D53/C41,""),"") -> 0.41602234
A56: OM expense test | B56: =IF(ISNUMBER(B53),IF(D53>B53*(1+Assumptions!$B$24),"OM EXPENSES LIGHT","OM expenses reasonable"),"OM expenses not published") -> OM expenses not published
A58: NOI & RETURNS
B59: OM as presented | C59: LAAA underwritten | F59: Basis / note
A60: Net operating income | C60: =IF(C37>0,C41-D53,"") -> 326280
A61: Cap rate on asking price | B61: =IFERROR(B60/B22,"") -> 0 | C61: =IF(C60="","",IFERROR(C60/B22,"")) -> 0.032628 | F61: OM column recomputed from OM figures; compare to published cap above
A62: GRM (price / scheduled rent) | B62: =IFERROR(B22/B37,"") | C62: =IF(C37>0,IFERROR(B22/C37,""),"") -> 17.361111
A63: NOI per unit | B63: =IFERROR(B60/B7,"") -> 0 | C63: =IF(C60="","",IFERROR(C60/B7,"")) -> 18126.667
A65: FINANCING (illustrative, on LAAA NOI)
A66: LTV loan | B66: =IFERROR(B22*Assumptions!$B$20,"") -> 6000000
A67: DCR-sized loan | B67: =IF(C60="","",IFERROR(PV(Assumptions!$B$22/12,Assumptions!$B$23*12,-C60/Assumptions!$B$21/12),"")) -> 3532790.7
A68: Loan amount (lesser of) | B68: =IFERROR(MIN(B66,B67),"") -> 3532790.7
A69: Down payment | B69: =IFERROR(B22-B68,"") -> 6467209.3
A70: Annual debt service | B70: =IFERROR(-PMT(Assumptions!$B$22/12,Assumptions!$B$23*12,B68)*12,"") -> 261024
A71: DCR | B71: =IFERROR(C60/B70,"") -> 1.25
A72: Cash flow after debt service | B72: =IFERROR(C60-B70,"") -> 65256
A73: Cash-on-cash return | B73: =IFERROR(B72/B69,"") -> 0.010090287
A75: Legend: yellow = published input, orange = estimated (nothing published), grey = LAAA underwritten (MAX of OM line and benchmark; taxes always reassessed).
